Workbook
Name ВременнаяШкала_Order_Date: #N/A
Name Срез_Customer_Name: #N/A
Name Срез_Product_Category: #N/A
Name Срез_Product_Sub_Category: #N/A

Sheet Orders
A1: Row ID | B1: Order Priority | C1: Discount | D1: Unit Price | E1: Shipping Cost | F1: Customer ID | G1: Customer Name | H1: Ship Mode | I1: Customer Segment | J1: Product Category | K1: Product Sub-Category | L1: Product Container | M1: Product Name | N1: Product Base Margin | O1: Country | P1: Region | Q1: State or Province | R1: City | S1: Postal Code | T1: Order Date | U1: Ship Date | V1: Profit | W1: Quantity ordered new | X1: Sales | Y1: Order ID
A2: 20847 | B2: High | C2: 0.01 | D2: 2.84 | E2: 0.93 | F2: 3 | G2: Bonnie Potter | H2: Express Air | I2: Corporate | J2: Office Supplies | K2: Pens & Art Supplies | L2: Wrap Bag | M2: SANFORD Liquid Accent™ Tank-Style Highlighters | N2: 0.54 | O2: United States | P2: West | Q2: Washington | R2: Anacortes | S2: 98221 | T2: 42011 | U2: 42012 | V2: 4.56 | W2: 4 | X2: 13.01 | Y2: 88522
A3: 20228 | B3: Not Specified | C3: 0.02 | D3: 500.98 | E3: 26 | F3: 5 | G3: Ronnie Proctor | H3: Delivery Truck | I3: Home Office | J3: Furniture | K3: Chairs & Chairmats | L3: Jumbo Drum | M3: Global Troy™ Executive Leather Low-Back Tilter | N3: 0.6 | O3: United States | P3: West | Q3: California | R3: San Gabriel | S3: 91776 | T3: 42168 | U3: 42170 | V3: 4390.3665 | W3: 12 | X3: 6362.85 | Y3: 90193
A4: 21776 | B4: Critical | C4: 0.06 | D4: 9.48 | E4: 7.29 | F4: 11 | G4: Marcus Dunlap | H4: Regular Air | I4: Home Office | J4: Furniture | K4: Office Furnishings | L4: Small Pack | M4: DAX Two-Tone Rosewood/Black Document Frame, Desktop, 5 x 7 | N4: 0.45 | O4: United States | P4: East | Q4: New Jersey | R4: Roselle | S4: 7203 | T4: 42050 | U4: 42052 | V4: -53.8096 | W4: 22 | X4: 211.15 | Y4: 90192
A5: 24844 | B5: Medium | C5: 0.09 | D5: 78.69 | E5: 19.99 | F5: 14 | G5: Gwendolyn F Tyson | H5: Regular Air | I5: Small Business | J5: Furniture | K5: Office Furnishings | L5: Small Box | M5: Howard Miller 12-3/4 Diameter Accuwave DS ™ Wall Clock | N5: 0.43 | O5: United States | P5: Central | Q5: Minnesota | R5: Prior Lake | S5: 55372 | T5: 42136 | U5: 42138 | V5: 803.4705 | W5: 16 | X5: 1164.45 | Y5: 86838
A6: 24846 | B6: Medium | C6: 0.08 | D6: 3.28 | E6: 2.31 | F6: 14 | G6: Gwendolyn F Tyson | H6: Regular Air | I6: Small Business | J6: Office Supplies | K6: Pens & Art Supplies | L6: Wrap Bag | M6: Newell 321 | N6: 0.56 | O6: United States | P6: Central | Q6: Minnesota | R6: Prior Lake | S6: 55372 | T6: 42136 | U6: 42137 | V6: -24.03 | W6: 7 | X6: 22.23 | Y6: 86838
A7: 24847 | B7: Medium | C7: 0.05 | D7: 3.28 | E7: 4.2 | F7: 14 | G7: Gwendolyn F Tyson | H7: Regular Air | I7: Small Business | J7: Office Supplies | K7: Pens & Art Supplies | L7: Wrap Bag | M7: Newell 351 | N7: 0.56 | O7: United States | P7: Central | Q7: Minnesota | R7: Prior Lake | S7: 55372 | T7: 42136 | U7: 42137 | V7: -37.03 | W7: 4 | X7: 13.99 | Y7: 86838
A8: 24848 | B8: Medium | C8: 0.05 | D8: 3.58 | E8: 1.63 | F8: 14 | G8: Gwendolyn F Tyson | H8: Regular Air | I8: Small Business | J8: Office Supplies | K8: Rubber Bands | L8: Wrap Bag | M8: OIC Colored Binder Clips, Assorted Sizes | N8: 0.36 | O8: United States | P8: Central | Q8: Minnesota | R8: Prior Lake | S8: 55372 | T8: 42136 | U8: 42137 | V8: -0.71 | W8: 4 | X8: 14.26 | Y8: 86838
A9: 18181 | B9: Critical | C9: 0 | D9: 4.42 | E9: 4.99 | F9: 15 | G9: Timothy Reese | H9: Regular Air | I9: Small Business | J9: Office Supplies | K9: Envelopes | L9: Small Box | M9: Grip Seal Envelopes | N9: 0.38 | O9: United States | P9: East | Q9: New York | R9: Smithtown | S9: 11787 | T9: 42102 | U9: 42103 | V9: -59.82 | W9: 7 | X9: 33.47 | Y9: 86837
A10: 20925 | B10: Medium | C10: 0.01 | D10: 35.94 | E10: 6.66 | F10: 15 | G10: Timothy Reese | H10: Regular Air | I10: Small Business | J10: Office Supplies | K10: Envelopes | L10: Small Box | M10: Tyvek ® Top-Opening Peel & Seel ® Envelopes, Gray | N10: 0.4 | O10: United States | P10: East | Q10: New York | R10: Smithtown | S10: 11787 | T10: 42152 | U10: 42152 | V10: 261.8757 | W10: 10 | X10: 379.53 | Y10: 86839
A11: 26267 | B11: High | C11: 0.04 | D11: 2.98 | E11: 1.58 | F11: 16 | G11: Sarah Ramsey | H11: Regular Air | I11: Small Business | J11: Office Supplies | K11: Rubber Bands | L11: Wrap Bag | M11: Staples Gold Paper Clips | N11: 0.39 | O11: United States | P11: East | Q11: New York | R11: Syracuse | S11: 13210 | T11: 42047 | U11: 42050 | V11: 2.63 | W11: 6 | X11: 18.8 | Y11: 86836
A12: 26268 | B12: High | C12: 0.05 | D12: 115.99 | E12: 2.5 | F12: 16 | G12: Sarah Ramsey | H12: Regular Air | I12: Small Business | J12: Technology | K12: Telephones and Communication | L12: Small Box | M12: StarTAC 7797 | N12: 0.55 | O12: United States | P12: East | Q12: New York | R12: Syracuse | S12: 13210 | T12: 42047 | U12: 42049 | V12: 652.7331 | W12: 10 | X12: 945.99 | Y12: 86836
A13: 23890 | B13: High | C13: 0.05 | D13: 26.48 | E13: 6.93 | F13: 18 | G13: Laurie Hanna | H13: Regular Air | I13: Small Business | J13: Furniture | K13: Office Furnishings | L13: Small Box | M13: DAX Natural Wood-Tone Poster Frame | N13: 0.49 | O13: United States | P13: West | Q13: Montana | R13: Helena | S13: 59601 | T13: 42139 | U13: 42140 | V13: 314.4813 | W13: 17 | X13: 455.77 | Y13: 90031
... A182: 19158 | B182: Medium | C182: 0.01 | D182: 29.1 | E182: 4 | F182: 331 | G182: Bradley Pollock | H182: Express Air | I182: Home Office | J182: Technology | K182: Computer Peripherals | L182: Small Box | M182: Acco Keyboard-In-A-Box® | N182: 0.78 | O182: United States | P182: East | Q182: New Hampshire | R182: Goffstown | S182: 3045 | T182: 42108 | U182: 42110 | V182: -22.82 | W182: 8 | X182: 243.32 | Y182: 89726
A183: 18261 | B183: Critical | C183: 0.06 | D183: 276.2 | E183: 24.49 | F183: 335 | G183: Curtis O'Connell | H183: Regular Air | I183: Corporate | J183: Furniture | K183: Chairs & Chairmats | L183: Large Box | M183: SAFCO Arco Folding Chair | O183: United States | P183: West | Q183: Oregon | R183: Medford | S183: 97504 | T183: 42128 | U183: 42129 | V183: 2639.4708 | W183: 14 | X183: 3825.32 | Y183: 87277
A184: 18262 | B184: Critical | C184: 0.09 | D184: 6.28 | E184: 5.29 | F184: 335 | G184: Curtis O'Connell | H184: Regular Air | I184: Corporate | J184: Furniture | K184: Office Furnishings | L184: Small Box | M184: Eldon® 200 Class™ Desk Accessories, Burgundy | N184: 0.43 | O184: United States | P184: West | Q184: Oregon | R184: Medford | S184: 97504 | T184: 42128 | U184: 42128 | V184: -5.2 | W184: 1 | X184: 8.53 | Y184: 87277
A185: 23481 | B185: Medium | C185: 0.08 | D185: 7.77 | E185: 9.23 | F185: 339 | G185: Bobby Clements | H185: Regular Air | I185: Corporate | J185: Office Supplies | K185: Appliances | L185: Small Box | M185: Hoover Commercial Soft Guard Upright Vacuum And Disposable Filtration Bags | N185: 0.58 | O185: United States | P185: East | Q185: Ohio | R185: Columbus | S185: 43229 | T185: 42080 | U185: 42081 | V185: -83.65 | W185: 5 | X185: 40.3 | Y185: 90583
A186: 23482 | B186: Medium | C186: 0.07 | D186: 7.59 | E186: 4 | F186: 339 | G186: Bobby Clements | H186: Regular Air | I186: Corporate | J186: Furniture | K186: Office Furnishings | L186: Wrap Bag | M186: Master Giant Foot® Doorstop, Safety Yellow | N186: 0.42 | O186: United States | P186: East | Q186: Ohio | R186: Columbus | S186: 43229 | T186: 42080 | U186: 42082 | V186: 24.39 | W186: 15 | X186: 111.88 | Y186: 90583
A187: 480 | B187: Critical | C187: 0.01 | D187: 3.26 | E187: 1.86 | F187: 342 | G187: Jacqueline Noble | H187: Regular Air | I187: Corporate | J187: Office Supplies | K187: Pens & Art Supplies | L187: Wrap Bag | M187: Avery Hi-Liter GlideStik Fluorescent Highlighter, Yellow Ink | N187: 0.41 | O187: United States | P187: South | Q187: Florida | R187: Miami | S187: 33181 | T187: 42128 | U187: 42130 | V187: -4.6683 | W187: 20 | X187: 73.97 | Y187: 3332
A188: 22784 | B188: Critical | C188: 0.03 | D188: 15.23 | E188: 27.75 | F188: 343 | G188: Lynn Epstein | H188: Delivery Truck | I188: Corporate | J188: Furniture | K188: Tables | L188: Jumbo Box | M188: Anderson Hickey Conga Table Tops & Accessories | N188: 0.76 | O188: United States | P188: East | Q188: Maine | R188: Bangor | S188: 4401 | T188: 42035 | U188: 42036 | V188: 11.65095 | W188: 7 | X188: 111.86 | Y188: 88151
A189: 18480 | B189: Critical | C189: 0.01 | D189: 3.26 | E189: 1.86 | F189: 344 | G189: Rosemary English | H189: Regular Air | I189: Corporate | J189: Office Supplies | K189: Pens & Art Supplies | L189: Wrap Bag | M189: Avery Hi-Liter GlideStik Fluorescent Highlighter, Yellow Ink | N189: 0.41 | O189: United States | P189: East | Q189: Maine | R189: Portland | S189: 4101 | T189: 42128 | U189: 42130 | V189: 0.702 | W189: 5 | X189: 18.49 | Y189: 88152
A190: 2408 | B190: Critical | C190: 0 | D190: 8.34 | E190: 2.64 | F190: 349 | G190: Kim Weiss | H190: Express Air | I190: Home Office | J190: Office Supplies | K190: Scissors, Rulers and Trimmers | L190: Small Pack | M190: Acme® Elite Stainless Steel Scissors | N190: 0.59 | O190: United States | P190: South | Q190: Florida | R190: Miami | S190: 33132 | T190: 42164 | U190: 42166 | V190: 5.8625 | W190: 23 | X190: 212.89 | Y190: 17446
A191: 1595 | B191: Medium | C191: 0.04 | D191: 99.23 | E191: 8.99 | F191: 349 | G191: Kim Weiss | H191: Regular Air | I191: Home Office | J191: Furniture | K191: Office Furnishings | L191: Small Pack | M191: GE 48" Fluorescent Tube, Cool White Energy Saver, 34 Watts, 30/Box | N191: 0.35 | O191: United States | P191: South | Q191: Florida | R191: Miami | S191: 33132 | T191: 42006 | U191: 42008 | V191: 1916.6757 | W191: 54 | X191: 5555.6 | Y191: 11527
A192: 20408 | B192: Critical | C192: 0 | D192: 8.34 | E192: 2.64 | F192: 351 | G192: Juanita Coley Knox | H192: Express Air | I192: Home Office | J192: Office Supplies | K192: Scissors, Rulers and Trimmers | L192: Small Pack | M192: Acme® Elite Stainless Steel Scissors | N192: 0.59 | O192: United States | P192: East | Q192: New York | R192: Watertown | S192: 13601 | T192: 42164 | U192: 42166 | V192: 10.5 | W192: 6 | X192: 55.54 | Y192: 88685
A193: 19595 | B193: Medium | C193: 0.04 | D193: 99.23 | E193: 8.99 | F193: 351 | G193: Juanita Coley Knox | H193: Regular Air | I193: Home Office | J193: Furniture | K193: Office Furnishings | L193: Small Pack | M193: GE 48" Fluorescent Tube, Cool White Energy Saver, 34 Watts, 30/Box | N193: 0.35 | O193: United States | P193: East | Q193: New York | R193: Watertown | S193: 13601 | T193: 42006 | U193: 42008 | V193: 993.8346 | W193: 14 | X193: 1440.34 | Y193: 88686
A194: 19107 | B194: Low | C194: 0.08 | D194: 4.89 | E194: 4.93 | F194: 353 | G194: Bonnie Chambers | H194: Express Air | I194: Home Office | J194: Technology | K194: Computer Peripherals | L194: Small Pack | M194: Maxell 3.5" DS/HD IBM-Formatted Diskettes, 10/Pack | N194: 0.66 | O194: United States | P194: West | Q194: Arizona | R194: Glendale | S194: 85301 | T194: 42138 | U194: 42138 | V194: -165.45 | W194: 17 | X194: 84.76 | Y194: 89647
A195: 19108 | B195: Low | C195: 0.07 | D195: 6.68 | E195: 6.92 | F195: 353 | G195: Bonnie Chambers | H195: Regular Air | I195: Home Office | J195: Office Supplies | K195: Paper | L195: Small Box | M195: Xerox 1898 | N195: 0.37 | O195: United States | P195: West | Q195: Arizona | R195: Glendale | S195: 85301 | T195: 42138 | U195: 42145 | V195: -141.12 | W195: 16 | X195: 104.84 | Y195: 89647
... A272: 21958 | B272: High | C272: 0.01 | D272: 20.98 | E272: 53.03 | F272: 508 | G272: Cameron Owens | H272: Delivery Truck | I272: Corporate | J272: Office Supplies | K272: Storage & Organization | L272: Jumbo Drum | M272: Tennsco Lockers, Gray | N272: 0.78 | O272: United States | P272: South | Q272: Kentucky | R272: Covington | S272: 41011 | T272: 42058 | U272: 42058 | V272: -282.0818 | W272: 5 | X272: 123 | Y272: 87356
A273: 18305 | B273: Critical | C273: 0.01 | D273: 128.24 | E273: 12.65 | F273: 508 | G273: Cameron Owens | H273: Regular Air | I273: Corporate | J273: Furniture | K273: Chairs & Chairmats | L273: Medium Box | M273: SAFCO Folding Chair Trolley | O273: United States | P273: South | Q273: Kentucky | R273: Covington | S273: 41011 | T273: 42112 | U273: 42115 | V273: 140.1354 | W273: 4 | X273: 554.08 | Y273: 87357
A274: 19895 | B274: Low | C274: 0.02 | D274: 48.04 | E274: 5.09 | F274: 510 | G274: Gregory Rao | H274: Regular Air | I274: Corporate | J274: Office Supplies | K274: Paper | L274: Small Box | M274: Xerox 1910 | N274: 0.37 | O274: United States | P274: West | Q274: California | R274: Manteca | S274: 95336 | T274: 42017 | U274: 42017 | V274: 105.2526 | W274: 3 | X274: 152.54 | Y274: 90058
A275: 20007 | B275: Critical | C275: 0.03 | D275: 6.37 | E275: 5.19 | F275: 510 | G275: Gregory Rao | H275: Regular Air | I275: Corporate | J275: Office Supplies | K275: Binders and Binder Accessories | L275: Small Box | M275: C-Line Peel & Stick Add-On Filing Pockets, 8-3/4 x 5-1/8, 10/Pack | N275: 0.38 | O275: United States | P275: West | Q275: California | R275: Manteca | S275: 95336 | T275: 42036 | U275: 42037 | V275: -29.0927 | W275: 14 | X275: 89.79 | Y275: 90059
A276: 20216 | B276: Low | C276: 0.07 | D276: 12.64 | E276: 4.98 | F276: 518 | G276: Mark Ritchie | H276: Regular Air | I276: Home Office | J276: Furniture | K276: Office Furnishings | L276: Small Pack | M276: Nu-Dell Executive Frame | N276: 0.48 | O276: United States | P276: Central | Q276: Missouri | R276: Clayton | S276: 63105 | T276: 42160 | U276: 42167 | V276: 113.415 | W276: 16 | X276: 199.76 | Y276: 90867
A277: 23200 | B277: Medium | C277: 0.02 | D277: 150.98 | E277: 13.99 | F277: 522 | G277: Aaron Riggs | H277: Express Air | I277: Small Business | J277: Technology | K277: Office Machines | L277: Medium Box | M277: Canon MP41DH Printing Calculator | N277: 0.38 | O277: United States | P277: West | Q277: Oregon | R277: Redmond | S277: 97756 | T277: 42177 | U277: 42179 | V277: 26.1 | W277: 3 | X277: 480.37 | Y277: 89327
A278: 23201 | B278: Medium | C278: 0.1 | D278: 5.43 | E278: 0.95 | F278: 522 | G278: Aaron Riggs | H278: Regular Air | I278: Small Business | J278: Office Supplies | K278: Paper | L278: Wrap Bag | M278: Wirebound Message Book, 4 per Page | N278: 0.36 | O278: United States | P278: West | Q278: Oregon | R278: Redmond | S278: 97756 | T278: 42177 | U278: 42179 | V278: -2.58 | W278: 1 | X278: 5.76 | Y278: 89327
A279: 23202 | B279: Medium | C279: 0.01 | D279: 179.29 | E279: 29.21 | F279: 522 | G279: Aaron Riggs | H279: Delivery Truck | I279: Small Business | J279: Furniture | K279: Tables | L279: Jumbo Box | M279: Bevis Round Conference Table Top, X-Base | N279: 0.74 | O279: United States | P279: West | Q279: Oregon | R279: Redmond | S279: 97756 | T279: 42177 | U279: 42178 | V279: 2800.12 | W279: 21 | X279: 3112.13 | Y279: 89327
A280: 21517 | B280: Not Specified | C280: 0.03 | D280: 1270.99 | E280: 19.99 | F280: 524 | G280: Gina McKnight | H280: Regular Air | I280: Consumer | J280: Office Supplies | K280: Binders and Binder Accessories | L280: Small Box | M280: Fellowes PB500 Electric Punch Plastic Comb Binding Machine with Manual Bind | N280: 0.35 | O280: United States | P280: South | Q280: Tennessee | R280: Farragut | S280: 37922 | T280: 42024 | U280: 42026 | V280: 363.552 | W280: 2 | X280: 2589.01 | Y280: 91127
A281: 21518 | B281: Not Specified | C281: 0.07 | D281: 2036.48 | E281: 14.7 | F281: 524 | G281: Gina McKnight | H281: Delivery Truck | I281: Consumer | J281: Technology | K281: Office Machines | L281: Jumbo Drum | M281: Lexmark 4227 Plus Dot Matrix Printer | N281: 0.55 | O281: United States | P281: South | Q281: Tennessee | R281: Farragut | S281: 37922 | T281: 42024 | U281: 42026 | V281: -11.536 | W281: 1 | X281: 1893.93 | Y281: 91127
A282: 22176 | B282: High | C282: 0.09 | D282: 17.98 | E282: 8.51 | F282: 526 | G282: April Hu | H282: Regular Air | I282: Home Office | J282: Technology | K282: Office Machines | L282: Medium Box | M282: Canon P1-DHIII Palm Printing Calculator | N282: 0.4 | O282: United States | P282: West | Q282: Arizona | R282: Mesa | S282: 85204 | T282: 42149 | U282: 42151 | V282: -6.612 | W282: 12 | X282: 211.13 | Y282: 90026
A283: 20494 | B283: Not Specified | C283: 0 | D283: 1.88 | E283: 1.49 | F283: 526 | G283: April Hu | H283: Regular Air | I283: Home Office | J283: Office Supplies | K283: Binders and Binder Accessories | L283: Small Box | M283: Staples® General Use 3-Ring Binders | N283: 0.37 | O283: United States | P283: West | Q283: Arizona | R283: Mesa | S283: 85204 | T283: 42021 | U283: 42022 | V283: -15.5595 | W283: 13 | X283: 25.39 | Y283: 90027
A284: 20495 | B284: Not Specified | C284: 0.06 | D284: 5.78 | E284: 5.67 | F284: 526 | G284: April Hu | H284: Regular Air | I284: Home Office | J284: Office Supplies | K284: Paper | L284: Small Box | M284: Xerox 1978 | N284: 0.36 | O284: United States | P284: West | Q284: Arizona | R284: Mesa | S284: 85204 | T284: 42021 | U284: 42022 | V284: -108.19 | W284: 15 | X284: 87.27 | Y284: 90027
A285: 26210 | B285: Low | C285: 0 | D285: 15.99 | E285: 13.18 | F285: 535 | G285: Jill Clements | H285: Regular Air | I285: Corporate | J285: Office Supplies | K285: Binders and Binder Accessories | L285: Small Box | M285: GBC Pre-Punched Binding Paper, Plastic, White, 8-1/2" x 11" | N285: 0.37 | O285: United States | P285: South | Q285: Virginia | R285: Montclair | S285: 22025 | T285: 42115 | U285: 42119 | V285: 46.488 | W285: 23 | X285: 403.25 | Y285: 88511
... A484: 24763 | B484: Critical | C484: 0.06 | D484: 6.48 | E484: 8.88 | F484: 868 | G484: Sharon Ellis | H484: Regular Air | I484: Corporate | J484: Office Supplies | K484: Paper | L484: Small Box | M484: Xerox 224 | N484: 0.37 | O484: United States | P484: Central | Q484: Minnesota | R484: Shoreview | S484: 55126 | T484: 42069 | U484: 42070 | V484: -237.47 | W484: 20 | X484: 125.77 | Y484: 91195
A485: 24764 | B485: Critical | C485: 0.09 | D485: 349.45 | E485: 60 | F485: 868 | G485: Sharon Ellis | H485: Delivery Truck | I485: Corporate | J485: Furniture | K485: Tables | L485: Jumbo Drum | M485: SAFCO PlanMaster Heigh-Adjustable Drafting Table Base, 43w x 30d x 30-37h, Black | O485: United States | P485: Central | Q485: Minnesota | R485: Shoreview | S485: 55126 | T485: 42069 | U485: 42070 | V485: -2946.051 | W485: 12 | X485: 3918.98 | Y485: 91195
A486: 25507 | B486: Not Specified | C486: 0.03 | D486: 14.2 | E486: 5.3 | F486: 871 | G486: Sandy Ellington | H486: Regular Air | I486: Home Office | J486: Furniture | K486: Office Furnishings | L486: Wrap Bag | M486: Coloredge Poster Frame | N486: 0.46 | O486: United States | P486: West | Q486: Nevada | R486: Reno | S486: 89502 | T486: 42078 | U486: 42080 | V486: 21.5556 | W486: 2 | X486: 31.24 | Y486: 90577
A487: 22547 | B487: Not Specified | C487: 0.01 | D487: 5.94 | E487: 9.92 | F487: 871 | G487: Sandy Ellington | H487: Regular Air | I487: Home Office | J487: Office Supplies | K487: Binders and Binder Accessories | L487: Small Box | M487: Storex Dura Pro™ Binders | N487: 0.38 | O487: United States | P487: West | Q487: Nevada | R487: Reno | S487: 89502 | T487: 42144 | U487: 42147 | V487: -239.315 | W487: 12 | X487: 74.77 | Y487: 90578
A488: 22548 | B488: Not Specified | C488: 0 | D488: 6.48 | E488: 5.11 | F488: 871 | G488: Sandy Ellington | H488: Regular Air | I488: Home Office | J488: Office Supplies | K488: Paper | L488: Small Box | M488: Xerox 231 | N488: 0.37 | O488: United States | P488: West | Q488: Nevada | R488: Reno | S488: 89502 | T488: 42144 | U488: 42146 | V488: -33.31 | W488: 18 | X488: 127.81 | Y488: 90578
A489: 19262 | B489: High | C489: 0.04 | D489: 4.37 | E489: 5.15 | F489: 875 | G489: Erika Fink | H489: Regular Air | I489: Small Business | J489: Office Supplies | K489: Appliances | L489: Small Box | M489: Eureka Sanitaire ® Multi-Pro Heavy-Duty Upright, Disposable Bags | N489: 0.59 | O489: United States | P489: West | Q489: Utah | R489: Salt Lake City | S489: 84106 | T489: 42056 | U489: 42057 | V489: -74.4796 | W489: 18 | X489: 78.59 | Y489: 89059
A490: 19263 | B490: High | C490: 0.09 | D490: 155.99 | E490: 8.99 | F490: 875 | G490: Erika Fink | H490: Regular Air | I490: Small Business | J490: Technology | K490: Telephones and Communication | L490: Small Box | M490: CF 688 | N490: 0.58 | O490: United States | P490: West | Q490: Utah | R490: Salt Lake City | S490: 84106 | T490: 42056 | U490: 42058 | V490: -232.22056 | W490: 4 | X490: 497.11 | Y490: 89059
A491: 18054 | B491: Critical | C491: 0.07 | D491: 5.68 | E491: 1.39 | F491: 880 | G491: Ellen Beck | H491: Regular Air | I491: Small Business | J491: Office Supplies | K491: Envelopes | L491: Small Box | M491: Staples Standard Envelopes | N491: 0.38 | O491: United States | P491: West | Q491: Arizona | R491: Scottsdale | S491: 85254 | T491: 42088 | U491: 42090 | V491: 18.6438 | W491: 5 | X491: 27.02 | Y491: 86153
A492: 18055 | B492: Critical | C492: 0.06 | D492: 22.84 | E492: 11.54 | F492: 880 | G492: Ellen Beck | H492: Regular Air | I492: Small Business | J492: Office Supplies | K492: Paper | L492: Small Box | M492: Xerox 1964 | N492: 0.39 | O492: United States | P492: West | Q492: Arizona | R492: Scottsdale | S492: 85254 | T492: 42088 | U492: 42090 | V492: -31.24 | W492: 1 | X492: 27.67 | Y492: 86153
A493: 19401 | B493: Critical | C493: 0.06 | D493: 25.98 | E493: 14.36 | F493: 885 | G493: Malcolm Robertson | H493: Delivery Truck | I493: Corporate | J493: Furniture | K493: Chairs & Chairmats | L493: Jumbo Drum | M493: Global Stack Chair without Arms, Black | N493: 0.6 | O493: United States | P493: Central | Q493: Texas | R493: Amarillo | S493: 79109 | T493: 42148 | U493: 42149 | V493: 55.888 | W493: 41 | X493: 1033.56 | Y493: 89537
A494: 26011 | B494: Critical | C494: 0.08 | D494: 1.81 | E494: 0.75 | F494: 890 | G494: Billie Fowler | H494: Regular Air | I494: Consumer | J494: Furniture | K494: Chairs & Chairmats | L494: Jumbo Drum | M494: Metal Folding Chairs, Beige, 4/Carton | N494: 0.58 | O494: United States | P494: Central | Q494: Texas | R494: Bedford | S494: 76021 | T494: 42009 | U494: 42010 | V494: 1.3224 | W494: 11 | X494: 19.97 | Y494: 89536
A495: 26015 | B495: Critical | C495: 0.04 | D495: 125.99 | E495: 5.26 | F495: 890 | G495: Billie Fowler | H495: Regular Air | I495: Consumer | J495: Technology | K495: Telephones and Communication | L495: Small Box | M495: 232 | N495: 0.55 | O495: United States | P495: Central | Q495: Texas | R495: Bedford | S495: 76021 | T495: 42009 | U495: 42009 | V495: 455.4207 | W495: 6 | X495: 660.03 | Y495: 89536
A496: 2045 | B496: Critical | C496: 0.01 | D496: 8.34 | E496: 0.96 | F496: 894 | G496: Gail Rankin Cole | H496: Regular Air | I496: Corporate | J496: Furniture | K496: Office Furnishings | L496: Wrap Bag | M496: Document Clip Frames | N496: 0.43 | O496: United States | P496: East | Q496: District of Columbia | R496: Washington | S496: 20024 | T496: 42014 | U496: 42016 | V496: 29.332 | W496: 24 | X496: 199.12 | Y496: 14596
A497: 2046 | B497: Critical | C497: 0.06 | D497: 3.28 | E497: 3.97 | F497: 894 | G497: Gail Rankin Cole | H497: Regular Air | I497: Corporate | J497: Office Supplies | K497: Pens & Art Supplies | L497: Wrap Bag | M497: Newell 337 | N497: 0.56 | O497: United States | P497: East | Q497: District of Columbia | R497: Washington | S497: 20024 | T497: 42014 | U497: 42015 | V497: -86 | W497: 19 | X497: 63.14 | Y497: 14596
... A661: 19184 | B661: High | C661: 0.09 | D661: 40.98 | E661: 6.5 | F661: 1178 | G661: Sandy Hunt | H661: Express Air | I661: Consumer | J661: Technology | K661: Computer Peripherals | L661: Small Box | M661: Targus USB Numeric Keypad | N661: 0.74 | O661: United States | P661: South | Q661: Florida | R661: Altamonte Springs | S661: 32701 | T661: 42103 | U661: 42105 | V661: 5.6916 | W661: 7 | X661: 267.69 | Y661: 89787
A662: 19185 | B662: High | C662: 0.09 | D662: 349.45 | E662: 60 | F662: 1178 | G662: Sandy Hunt | H662: Delivery Truck | I662: Consumer | J662: Furniture | K662: Tables | L662: Jumbo Drum | M662: SAFCO PlanMaster Heigh-Adjustable Drafting Table Base, 43w x 30d x 30-37h, Black | O662: United States | P662: South | Q662: Florida | R662: Altamonte Springs | S662: 32701 | T662: 42103 | U662: 42104 | V662: -369.11 | W662: 7 | X662: 2307.26 | Y662: 89787
A663: 19484 | B663: High | C663: 0.07 | D663: 2.61 | E663: 0.5 | F663: 1182 | G663: Jesse Williamson | H663: Regular Air | I663: Home Office | J663: Office Supplies | K663: Labels | L663: Small Box | M663: Avery 494 | N663: 0.39 | O663: United States | P663: West | Q663: Utah | R663: Spanish Fork | S663: 84660 | T663: 42147 | U663: 42147 | V663: 27.0135 | W663: 15 | X663: 39.15 | Y663: 86913
A664: 21522 | B664: Not Specified | C664: 0.04 | D664: 35.99 | E664: 3.3 | F664: 1183 | G664: Becky O'Brien | H664: Regular Air | I664: Home Office | J664: Technology | K664: Telephones and Communication | L664: Small Pack | M664: Accessory9 | N664: 0.39 | O664: United States | P664: West | Q664: Utah | R664: Springville | S664: 84663 | T664: 42184 | U664: 42184 | V664: 184.1955 | W664: 9 | X664: 266.95 | Y664: 86914
A665: 22190 | B665: Medium | C665: 0 | D665: 6783.02 | E665: 24.49 | F665: 1185 | G665: Lee Xu | H665: Regular Air | I665: Consumer | J665: Technology | K665: Office Machines | L665: Large Box | M665: Polycom ViewStation™ ISDN Videoconferencing Unit | N665: 0.39 | O665: United States | P665: South | Q665: Alabama | R665: Madison | S665: 35756 | T665: 42084 | U665: 42085 | V665: 4.11 | W665: 3 | X665: 20552.55 | Y665: 85938
A666: 20764 | B666: Not Specified | C666: 0.08 | D666: 11.7 | E666: 6.96 | F666: 1185 | G666: Lee Xu | H666: Regular Air | I666: Consumer | J666: Office Supplies | K666: Appliances | L666: Medium Box | M666: Harmony HEPA Quiet Air Purifiers | N666: 0.5 | O666: United States | P666: South | Q666: Alabama | R666: Madison | S666: 35756 | T666: 42104 | U666: 42107 | V666: 28.566 | W666: 8 | X666: 87.8 | Y666: 85940
A667: 24358 | B667: Critical | C667: 0.07 | D667: 400.97 | E667: 48.26 | F667: 1186 | G667: Glenda Herbert | H667: Delivery Truck | I667: Consumer | J667: Technology | K667: Office Machines | L667: Jumbo Box | M667: Hewlett-Packard Deskjet 1220Cse Color Inkjet Printer | N667: 0.36 | O667: United States | P667: West | Q667: California | R667: Huntington Beach | S667: 92646 | T667: 42103 | U667: 42104 | V667: 2581.5591 | W667: 10 | X667: 3741.39 | Y667: 85939
A668: 18829 | B668: Low | C668: 0.06 | D668: 10.89 | E668: 4.5 | F668: 1189 | G668: Dwight Stephenson | H668: Regular Air | I668: Consumer | J668: Office Supplies | K668: Appliances | L668: Small Box | M668: Belkin 6 Outlet Metallic Surge Strip | N668: 0.59 | O668: United States | P668: West | Q668: California | R668: Huntington Beach | S668: 92646 | T668: 42172 | U668: 42177 | V668: -25.112 | W668: 14 | X668: 149.32 | Y668: 87584
A669: 18830 | B669: Low | C669: 0.03 | D669: 10.64 | E669: 5.16 | F669: 1189 | G669: Dwight Stephenson | H669: Regular Air | I669: Consumer | J669: Furniture | K669: Office Furnishings | L669: Small Box | M669: Eldon Expressions Punched Metal & Wood Desk Accessories, Pewter & Cherry | N669: 0.57 | O669: United States | P669: West | Q669: California | R669: Huntington Beach | S669: 92646 | T669: 42172 | U669: 42177 | V669: 17.376 | W669: 16 | X669: 177.01 | Y669: 87584
A670: 18831 | B670: Low | C670: 0.03 | D670: 7.96 | E670: 4.95 | F670: 1189 | G670: Dwight Stephenson | H670: Regular Air | I670: Consumer | J670: Furniture | K670: Office Furnishings | L670: Small Box | M670: Staples Plastic Wall Frames | N670: 0.41 | O670: United States | P670: West | Q670: California | R670: Huntington Beach | S670: 92646 | T670: 42172 | U670: 42174 | V670: 24.2604 | W670: 4 | X670: 35.16 | Y670: 87584
A671: 19553 | B671: Low | C671: 0.03 | D671: 28.53 | E671: 1.49 | F671: 1191 | G671: John Morse | H671: Regular Air | I671: Small Business | J671: Office Supplies | K671: Binders and Binder Accessories | L671: Small Box | M671: Lock-Up Easel 'Spel-Binder' | N671: 0.38 | O671: United States | P671: East | Q671: Connecticut | R671: New Britain | S671: 6050 | T671: 42183 | U671: 42186 | V671: 59.4405 | W671: 3 | X671: 88.84 | Y671: 87587
A672: 830 | B672: Low | C672: 0.03 | D672: 10.64 | E672: 5.16 | F672: 1193 | G672: Louis Parrish | H672: Regular Air | I672: Consumer | J672: Furniture | K672: Office Furnishings | L672: Small Box | M672: Eldon Expressions Punched Metal & Wood Desk Accessories, Pewter & Cherry | N672: 0.57 | O672: United States | P672: East | Q672: District of Columbia | R672: Washington | S672: 20016 | T672: 42172 | U672: 42177 | V672: 14.48 | W672: 63 | X672: 696.96 | Y672: 5984
A673: 831 | B673: Low | C673: 0.03 | D673: 7.96 | E673: 4.95 | F673: 1193 | G673: Louis Parrish | H673: Regular Air | I673: Consumer | J673: Furniture | K673: Office Furnishings | L673: Small Box | M673: Staples Plastic Wall Frames | N673: 0.41 | O673: United States | P673: East | Q673: District of Columbia | R673: Washington | S673: 20016 | T673: 42172 | U673: 42174 | V673: 22.25 | W673: 17 | X673: 149.41 | Y673: 5984
A674: 4131 | B674: High | C674: 0.05 | D674: 52.4 | E674: 16.11 | F674: 1193 | G674: Louis Parrish | H674: Regular Air | I674: Consumer | J674: Office Supplies | K674: Binders and Binder Accessories | L674: Small Box | M674: Ibico Laser Imprintable Binding System Covers | N674: 0.39 | O674: United States | P674: East | Q674: District of Columbia | R674: Washington | S674: 20016 | T674: 42060 | U674: 42062 | V674: 592.5265 | W674: 85 | X674: 4556.63 | Y674: 29350
... A701: 19875 | B701: High | C701: 0.04 | D701: 205.99 | E701: 5.26 | F701: 1233 | G701: Gary Hester | H701: Regular Air | I701: Consumer | J701: Technology | K701: Telephones and Communication | L701: Small Box | M701: i470 | N701: 0.56 | O701: United States | P701: Central | Q701: Texas | R701: Flower Mound | S701: 75028 | T701: 42159 | U701: 42160 | V701: -0.814 | W701: 6 | X701: 1018.61 | Y701: 89376
A702: 20592 | B702: Medium | C702: 0.03 | D702: 128.24 | E702: 12.65 | F702: 1237 | G702: Eva Simpson | H702: Regular Air | I702: Corporate | J702: Furniture | K702: Chairs & Chairmats | L702: Medium Box | M702: SAFCO Folding Chair Trolley | O702: United States | P702: Central | Q702: Texas | R702: Carrollton | S702: 75007 | T702: 42035 | U702: 42037 | V702: 790.464 | W702: 9 | X702: 1145.6 | Y702: 86075
A703: 18625 | B703: Not Specified | C703: 0.02 | D703: 7.38 | E703: 5.21 | F703: 1237 | G703: Eva Simpson | H703: Regular Air | I703: Corporate | J703: Furniture | K703: Office Furnishings | L703: Small Box | M703: Eldon® Expressions™ Wood Desk Accessories, Oak | N703: 0.56 | O703: United States | P703: Central | Q703: Texas | R703: Carrollton | S703: 75007 | T703: 42092 | U703: 42093 | V703: 7.74 | W703: 3 | X703: 24.52 | Y703: 86076
A704: 20432 | B704: Medium | C704: 0.05 | D704: 300.98 | E704: 13.99 | F704: 1237 | G704: Eva Simpson | H704: Regular Air | I704: Corporate | J704: Technology | K704: Office Machines | L704: Medium Box | M704: Polycom VoiceStation 100 | N704: 0.39 | O704: United States | P704: Central | Q704: Texas | R704: Carrollton | S704: 75007 | T704: 42149 | U704: 42150 | V704: 3985.3089 | W704: 20 | X704: 5775.81 | Y704: 86077
A705: 20433 | B705: Medium | C705: 0.04 | D705: 205.99 | E705: 5 | F705: 1237 | G705: Eva Simpson | H705: Express Air | I705: Corporate | J705: Technology | K705: Telephones and Communication | L705: Small Box | M705: Phone 918 | N705: 0.59 | O705: United States | P705: Central | Q705: Texas | R705: Carrollton | S705: 75007 | T705: 42149 | U705: 42150 | V705: 13.9568 | W705: 11 | X705: 1878.24 | Y705: 86077
A706: 20593 | B706: Medium | C706: 0.01 | D706: 160.98 | E706: 30 | F706: 1238 | G706: April Bowers | H706: Delivery Truck | I706: Corporate | J706: Furniture | K706: Chairs & Chairmats | L706: Jumbo Drum | M706: Office Star - Mid Back Dual function Ergonomic High Back Chair with 2-Way Adjustable Arms | N706: 0.62 | O706: United States | P706: Central | Q706: Texas | R706: Cedar Hill | S706: 75104 | T706: 42035 | U706: 42037 | V706: 788.79 | W706: 10 | X706: 1634.67 | Y706: 86075
A707: 20920 | B707: Not Specified | C707: 0 | D707: 387.99 | E707: 19.99 | F707: 1241 | G707: Bradley Schroeder | H707: Regular Air | I707: Corporate | J707: Office Supplies | K707: Binders and Binder Accessories | L707: Small Box | M707: Fellowes PB300 Plastic Comb Binding Machine | N707: 0.38 | O707: United States | P707: South | Q707: Alabama | R707: Auburn | S707: 36830 | T707: 42079 | U707: 42080 | V707: -70.14 | W707: 23 | X707: 9280.72 | Y707: 90880
A708: 20233 | B708: Critical | C708: 0.06 | D708: 200.97 | E708: 15.59 | F708: 1241 | G708: Bradley Schroeder | H708: Delivery Truck | I708: Small Business | J708: Technology | K708: Office Machines | L708: Jumbo Drum | M708: Hewlett-Packard Deskjet 6122 Color Inkjet Printer | N708: 0.36 | O708: United States | P708: South | Q708: Alabama | R708: Auburn | S708: 36830 | T708: 42088 | U708: 42088 | V708: 531.618 | W708: 7 | X708: 1348.83 | Y708: 90881
A709: 5117 | B709: High | C709: 0.1 | D709: 22.38 | E709: 15.1 | F709: 1246 | G709: Lois Hansen | H709: Regular Air | I709: Home Office | J709: Office Supplies | K709: Binders and Binder Accessories | L709: Small Box | M709: Avery Flip-Chart Easel Binder, Black | N709: 0.38 | O709: United States | P709: East | Q709: New York | R709: New York City | S709: 10009 | T709: 42099 | U709: 42100 | V709: -107.5135 | W709: 26 | X709: 564.98 | Y709: 36452
A710: 5118 | B710: High | C710: 0.04 | D710: 6.98 | E710: 2.83 | F710: 1246 | G710: Lois Hansen | H710: Regular Air | I710: Home Office | J710: Furniture | K710: Office Furnishings | L710: Small Pack | M710: G.E. Halogen Desk Lamp Bulbs | N710: 0.37 | O710: United States | P710: East | Q710: New York | R710: New York City | S710: 10009 | T710: 42099 | U710: 42101 | V710: 46.01 | W710: 18 | X710: 129.48 | Y710: 36452
A711: 6581 | B711: Low | C711: 0.03 | D711: 256.99 | E711: 11.25 | F711: 1246 | G711: Lois Hansen | H711: Regular Air | I711: Home Office | J711: Technology | K711: Computer Peripherals | L711: Small Box | M711: Hayes Optima 56K V.90 Internal Voice Modem | N711: 0.51 | O711: United States | P711: East | Q711: New York | R711: New York City | S711: 10009 | T711: 42146 | U711: 42146 | V711: 1489.8 | W711: 32 | X711: 8216.28 | Y711: 46853
A712: 23117 | B712: High | C712: 0.1 | D712: 22.38 | E712: 15.1 | F712: 1247 | G712: Henry O'Connell | H712: Regular Air | I712: Home Office | J712: Office Supplies | K712: Binders and Binder Accessories | L712: Small Box | M712: Avery Flip-Chart Easel Binder, Black | N712: 0.38 | O712: United States | P712: Central | Q712: Texas | R712: Leander | S712: 78641 | T712: 42099 | U712: 42100 | V712: -107.5135 | W712: 7 | X712: 152.11 | Y712: 91555
A713: 23118 | B713: High | C713: 0.04 | D713: 6.98 | E713: 2.83 | F713: 1247 | G713: Henry O'Connell | H713: Regular Air | I713: Home Office | J713: Furniture | K713: Office Furnishings | L713: Small Pack | M713: G.E. Halogen Desk Lamp Bulbs | N713: 0.37 | O713: United States | P713: Central | Q713: Texas | R713: Leander | S713: 78641 | T713: 42099 | U713: 42101 | V713: 24.8193 | W713: 5 | X713: 35.97 | Y713: 91555
A714: 18413 | B714: High | C714: 0 | D714: 3.89 | E714: 7.01 | F714: 1250 | G714: Kara Patton | H714: Regular Air | I714: Corporate | J714: Office Supplies | K714: Binders and Binder Accessories | L714: Small Box | M714: Avery Binder Labels | N714: 0.37 | O714: United States | P714: Central | Q714: Illinois | R714: Carpentersville | S714: 60110 | T714: 42103 | U714: 42103 | V714: -255.1689 | W714: 21 | X714: 85.64 | Y714: 87877
... A728: 22363 | B728: Critical | C728: 0.01 | D728: 13.99 | E728: 7.51 | F728: 1267 | G728: Rosemary Branch | H728: Regular Air | I728: Corporate | J728: Technology | K728: Office Machines | L728: Medium Box | M728: Sharp EL500L Fraction Calculator | N728: 0.39 | O728: United States | P728: South | Q728: Florida | R728: Boca Raton | S728: 33433 | T728: 42045 | U728: 42046 | V728: 533.742 | W728: 2 | X728: 29.85 | Y728: 89514
A729: 21848 | B729: Not Specified | C729: 0.08 | D729: 128.24 | E729: 12.65 | F729: 1267 | G729: Rosemary Branch | H729: Regular Air | I729: Corporate | J729: Furniture | K729: Chairs & Chairmats | L729: Medium Box | M729: SAFCO Folding Chair Trolley | O729: United States | P729: South | Q729: Florida | R729: Boca Raton | S729: 33433 | T729: 42136 | U729: 42137 | V729: -379.344 | W729: 3 | X729: 366.44 | Y729: 89515
A730: 21849 | B730: Not Specified | C730: 0.04 | D730: 5.98 | E730: 4.38 | F730: 1267 | G730: Rosemary Branch | H730: Regular Air | I730: Corporate | J730: Technology | K730: Computer Peripherals | L730: Small Pack | M730: Imation 3.5" DS/HD IBM Formatted Diskettes, 10/Pack | N730: 0.75 | O730: United States | P730: South | Q730: Florida | R730: Boca Raton | S730: 33433 | T730: 42136 | U730: 42138 | V730: -1522.304 | W730: 11 | X730: 69.75 | Y730: 89515
A731: 19550 | B731: Medium | C731: 0.07 | D731: 125.99 | E731: 7.69 | F731: 1271 | G731: Joanne Church | H731: Regular Air | I731: Corporate | J731: Technology | K731: Telephones and Communication | L731: Small Box | M731: StarTAC 3000 | N731: 0.59 | O731: United States | P731: West | Q731: California | R731: La Mesa | S731: 91941 | T731: 42103 | U731: 42104 | V731: 588.2457 | W731: 8 | X731: 852.53 | Y731: 88410
A732: 19398 | B732: Low | C732: 0.1 | D732: 34.23 | E732: 5.02 | F732: 1271 | G732: Joanne Church | H732: Regular Air | I732: Corporate | J732: Furniture | K732: Office Furnishings | L732: Small Box | M732: Hand-Finished Solid Wood Document Frame | N732: 0.55 | O732: United States | P732: West | Q732: California | R732: La Mesa | S732: 91941 | T732: 42125 | U732: 42130 | V732: 151.5654 | W732: 7 | X732: 219.66 | Y732: 88411
A733: 20628 | B733: Critical | C733: 0.07 | D733: 40.98 | E733: 7.47 | F733: 1279 | G733: Josephine Rao | H733: Regular Air | I733: Corporate | J733: Office Supplies | K733: Binders and Binder Accessories | L733: Small Box | M733: Wilson Jones Ledger-Size, Piano-Hinge Binder, 2", Blue | N733: 0.37 | O733: United States | P733: Central | Q733: Indiana | R733: Hammond | S733: 46324 | T733: 42064 | U733: 42065 | V733: 54.9015 | W733: 2 | X733: 81.9 | Y733: 90114
A734: 25005 | B734: Not Specified | C734: 0 | D734: 442.14 | E734: 14.7 | F734: 1279 | G734: Josephine Rao | H734: Delivery Truck | I734: Corporate | J734: Technology | K734: Office Machines | L734: Jumbo Drum | M734: Okidata ML390 Turbo Dot Matrix Printers | N734: 0.56 | O734: United States | P734: Central | Q734: Indiana | R734: Hammond | S734: 46324 | T734: 42068 | U734: 42068 | V734: 501.51 | W734: 5 | X734: 2343.34 | Y734: 90115
A735: 2628 | B735: Critical | C735: 0.07 | D735: 40.98 | E735: 7.47 | F735: 1280 | G735: Harold Albright | H735: Regular Air | I735: Corporate | J735: Office Supplies | K735: Binders and Binder Accessories | L735: Small Box | M735: Wilson Jones Ledger-Size, Piano-Hinge Binder, 2", Blue | N735: 0.37 | O735: United States | P735: West | Q735: Washington | R735: Seattle | S735: 98119 | T735: 42064 | U735: 42065 | V735: 54.9015 | W735: 8 | X735: 327.61 | Y735: 19042
A736: 22125 | B736: Low | C736: 0.1 | D736: 238.4 | E736: 24.49 | F736: 1281 | G736: Pauline Denton | H736: Regular Air | I736: Small Business | J736: Furniture | K736: Chairs & Chairmats | L736: Large Box | M736: Safco Contoured Stacking Chairs | O736: United States | P736: Central | Q736: Indiana | R736: Vincennes | S736: 47591 | T736: 42028 | U736: 42030 | V736: 875.2844 | W736: 8 | X736: 1774.5 | Y736: 89112
A737: 22126 | B737: Low | C737: 0.03 | D737: 199.99 | E737: 24.49 | F737: 1281 | G737: Pauline Denton | H737: Express Air | I737: Small Business | J737: Technology | K737: Copiers and Fax | L737: Large Box | M737: Canon PC-428 Personal Copier | N737: 0.46 | O737: United States | P737: Central | Q737: Indiana | R737: Vincennes | S737: 47591 | T737: 42028 | U737: 42030 | V737: 727.7361 | W737: 5 | X737: 1054.69 | Y737: 89112
A738: 4125 | B738: Low | C738: 0.1 | D738: 238.4 | E738: 24.49 | F738: 1282 | G738: Dana Sharpe | H738: Regular Air | I738: Small Business | J738: Furniture | K738: Chairs & Chairmats | L738: Large Box | M738: Safco Contoured Stacking Chairs | O738: United States | P738: East | Q738: Pennsylvania | R738: Philadelphia | S738: 19134 | T738: 42028 | U738: 42030 | V738: 460.676 | W738: 30 | X738: 6654.39 | Y738: 29319
A739: 4126 | B739: Low | C739: 0.03 | D739: 199.99 | E739: 24.49 | F739: 1282 | G739: Dana Sharpe | H739: Express Air | I739: Small Business | J739: Technology | K739: Copiers and Fax | L739: Large Box | M739: Canon PC-428 Personal Copier | N739: 0.46 | O739: United States | P739: East | Q739: Pennsylvania | R739: Philadelphia | S739: 19134 | T739: 42028 | U739: 42030 | V739: 393.42 | W739: 21 | X739: 4429.69 | Y739: 29319
A740: 19990 | B740: Not Specified | C740: 0.04 | D740: 150.98 | E740: 13.99 | F740: 1298 | G740: Herbert Beard | H740: Regular Air | I740: Home Office | J740: Technology | K740: Office Machines | L740: Medium Box | M740: Canon MP41DH Printing Calculator | N740: 0.38 | O740: United States | P740: Central | Q740: Texas | R740: Sulphur Springs | S740: 75482 | T740: 42047 | U740: 42050 | V740: 606.0546 | W740: 6 | X740: 878.34 | Y740: 90662
A741: 19991 | B741: Not Specified | C741: 0.04 | D741: 176.19 | E741: 11.87 | F741: 1298 | G741: Herbert Beard | H741: Regular Air | I741: Home Office | J741: Office Supplies | K741: Storage & Organization | L741: Small Box | M741: Fellowes High-Stak® Drawer Files | N741: 0.62 | O741: United States | P741: Central | Q741: Texas | R741: Sulphur Springs | S741: 75482 | T741: 42047 | U741: 42049 | V741: 320.1 | W741: 4 | X741: 676.57 | Y741: 90662
A742: 23120 | B742: High | C742: 0.03 | D742: 39.48 | E742: 1.99 | F742: 1303 | G742: Cindy Harvey | H742: Regular Air | I742: Consumer | J742: Technology | K742: Computer Peripherals | L742: Small Pack | M742: 80 Minute CD-R Spindle, 100/Pack - Staples | N742: 0.54 | O742: United States | P742: West | Q742: Utah | R742: Tooele | S742: 84074 | T742: 42054 | U742: 42056 | V742: 317.0895 | W742: 12 | X742: 459.55 | Y742: 87003
A743: 20652 | B743: Low | C743: 0.01 | D743: 65.99 | E743: 5.31 | F743: 1303 | G743: Cindy Harvey | H743: Regular Air | I743: Consumer | J743: Technology | K743: Telephones and Communication | L743: Small Box | M743: 3390 | N743: 0.57 | O743: United States | P743: West | Q743: Utah | R743: Tooele | S743: 84074 | T743: 42054 | U743: 42061 | V743: 250.36272 | W743: 9 | X743: 536.9 | Y743: 87005
A744: 25092 | B744: Medium | C744: 0.08 | D744: 2.88 | E744: 0.5 | F744: 1304 | G744: Sherri McIntosh | H744: Regular Air | I744: Consumer | J744: Office Supplies | K744: Labels | L744: Small Box | M744: Avery 507 | N744: 0.39 | O744: United States | P744: West | Q744: Utah | R744: West Jordan | S744: 84084 | T744: 42117 | U744: 42118 | V744: 6.0306 | W744: 3 | X744: 8.74 | Y744: 87004
...

Sheet Users
A1: Region | B1: Manager
A2: Central | B2: Chris
A3: East | B3: Erin
A4: South | B4: Sam
A5: West | B5: William

Sheet выручка по менеджерам
E5: Процент выручки по менеджерам
E6: менеджер | F6: выручка
E7: Chris | F7: 448284.7
E8: Erin | F8: 592171.49
E9: Sam | F9: 357105.12
E10: William | F10: 526776.57
E11: Общий итог | F11: 1924337.9

Sheet kpi
C4: выручка | D4: прибыль | E4: средний чек
C5: 1924337.9 | D5: 224077.61 | E5: 1409.7713

Sheet выручка от даты
B3: выручка, тыс.
B4: Названия строк | C4: выручка | D4: выручка2
B5: янв | C5: 274766.92 | D5: 274766.92
B6: фев | C6: 326101.47 | D6: 326101.47
B7: мар | C7: 271696.67 | D7: 271696.67
B8: апр | C8: 389831.95 | D8: 389831.95
B9: май | C9: 306572.07 | D9: 306572.07
B10: июн | C10: 355368.8 | D10: 355368.8

Sheet покупатели
B4: Названия строк | C4: выручка
B5: Aaron Day | C5: 710.16
B6: Aaron Dillon | C6: 18.34
B7: Aaron Riggs | C7: 3598.26
B8: Aaron Shaffer | C8: 894.64
B9: Adam G Sawyer | C9: 1638.5
B10: Adam Saunders Gray | C10: 48.3
B11: Albert Frost | C11: 485.01
B12: Albert Maxwell | C12: 396.19
B13: Albert Tyson | C13: 1338.6
B14: Alex Harrell | C14: 267.89
B15: Alex Nicholson | C15: 191.68
B16: Alex Watkins | C16: 205.76
... B1135: Общий итог | C1135: 1924337.9

Sheet топ 5 товаров
B2: топ 5 товаров
B3: Названия строк | C3: выручка
B4: Polycom ViewStation™ ISDN Videoconferencing Unit | C4: 46538.69
B5: Okidata ML395C Color Dot Matrix Printer | C5: 47611.09
B6: Global Troy™ Executive Leather Low-Back Tilter | C6: 50871.21
B7: Lexmark 4227 Plus Dot Matrix Printer | C7: 61071.73
B8: Fellowes PB500 Electric Punch Plastic Comb Binding Machine with Manual Bind | C8: 69013.48

Sheet сегмент
B2: доход по сегменту покупателя
B3: Названия строк | C3: выручка
B4: Corporate | C4: 657784.53
B5: Home Office | C5: 464481.04
B6: Consumer | C6: 401778.37
B7: Small Business | C7: 400293.94
B8: Общий итог | C8: 1924337.9

Sheet Дашборд

Sheet формулы
B7: Order ID | C7: Order Date | D7: Product_id | E7: Profit | F7: Region | G7: Product_name | H7: Manager | I7: Is_Xerox | O7: Прибыль для каждого менеджера в феврале
B8: 86838 | C8: 42136 | D8: 4 | E8: 803.4705 | F8: Central | G8: =VLOOKUP(D8,products[],4,0) -> Howard Miller 12-3/4 Diameter Accuwave DS ™ Wall Clock | H8: =INDEX(Таблица3[],MATCH(формулы!F8,Таблица3[Region],0),2) -> Chris | I8: =IF(ISNUMBER(SEARCH("Xerox",G8)), "да", "нет") -> нет
B9: 91304 | C9: 42050 | D9: 4 | E9: 465.4395 | F9: West | G9: =VLOOKUP(D9,products[],4,0) -> Howard Miller 12-3/4 Diameter Accuwave DS ™ Wall Clock | H9: =INDEX(Таблица3[],MATCH(формулы!F9,Таблица3[Region],0),2) -> William | I9: =IF(ISNUMBER(SEARCH("Xerox",G9)), "да", "нет") -> нет | K9: =COUNTIF(I8:I1959, "да") -> 173 | O9: Chris | P9: Erin | Q9: Sam | R9: William
B10: 91454 | C10: 42134 | D10: 24 | E10: 25.91382 | F10: West | G10: =VLOOKUP(D10,products[],4,0) -> AT&T 2230 Dual Handset Phone With Caller ID/Call Waiting | H10: =INDEX(Таблица3[],MATCH(формулы!F10,Таблица3[Region],0),2) -> William | I10: =IF(ISNUMBER(SEARCH("Xerox",G10)), "да", "нет") -> нет | O10: =SUMIFS($E$8:$E$1959,$C$8:$C$1959,"<01.03.2015",$C$8:$C$1959,">=01.02.2015",$H$8:$H$1959,O9) -> 19971.093 | P10: =SUMIFS($E$8:$E$1959,$C$8:$C$1959,"<01.03.2015",$C$8:$C$1959,">=01.02.2015",$H$8:$H$1959,P9) -> -3273.2288 | Q10: =SUMIFS($E$8:$E$1959,$C$8:$C$1959,"<01.03.2015",$C$8:$C$1959,">=01.02.2015",$H$8:$H$1959,Q9) -> -8583.7102 | R10: =SUMIFS($E$8:$E$1959,$C$8:$C$1959,"<01.03.2015",$C$8:$C$1959,">=01.02.2015",$H$8:$H$1959,R9) -> 27830.505
B11: 87366 | C11: 42093 | D11: 40 | E11: 7402.32 | F11: East | G11: =VLOOKUP(D11,products[],4,0) -> GBC DocuBind TL300 Electric Binding System | H11: =INDEX(Таблица3[],MATCH(формулы!F11,Таблица3[Region],0),2) -> Erin | I11: =IF(ISNUMBER(SEARCH("Xerox",G11)), "да", "нет") -> нет
B12: 85826 | C12: 42012 | D12: 40 | E12: 3602.1312 | F12: West | G12: =VLOOKUP(D12,products[],4,0) -> GBC DocuBind TL300 Electric Binding System | H12: =INDEX(Таблица3[],MATCH(формулы!F12,Таблица3[Region],0),2) -> William | I12: =IF(ISNUMBER(SEARCH("Xerox",G12)), "да", "нет") -> нет
B13: 90596 | C13: 42158 | D13: 41 | E13: 1892.424 | F13: West | G13: =VLOOKUP(D13,products[],4,0) -> Fellowes Super Stor/Drawer® Files | H13: =INDEX(Таблица3[],MATCH(формулы!F13,Таблица3[Region],0),2) -> William | I13: =IF(ISNUMBER(SEARCH("Xerox",G13)), "да", "нет") -> нет
B14: 88921 | C14: 42096 | D14: 41 | E14: 1167.158 | F14: Central | G14: =VLOOKUP(D14,products[],4,0) -> Fellowes Super Stor/Drawer® Files | H14: =INDEX(Таблица3[],MATCH(формулы!F14,Таблица3[Region],0),2) -> Chris | I14: =IF(ISNUMBER(SEARCH("Xerox",G14)), "да", "нет") -> нет
B15: 51072 | C15: 42096 | D15: 41 | E15: 1014.92 | F15: Central | G15: =VLOOKUP(D15,products[],4,0) -> Fellowes Super Stor/Drawer® Files | H15: =INDEX(Таблица3[],MATCH(формулы!F15,Таблица3[Region],0),2) -> Chris | I15: =IF(ISNUMBER(SEARCH("Xerox",G15)), "да", "нет") -> нет
B16: 88174 | C16: 42006 | D16: 41 | E16: -7.58 | F16: Central | G16: =VLOOKUP(D16,products[],4,0) -> Fellowes Super Stor/Drawer® Files | H16: =INDEX(Таблица3[],MATCH(формулы!F16,Таблица3[Region],0),2) -> Chris | I16: =IF(ISNUMBER(SEARCH("Xerox",G16)), "да", "нет") -> нет
B17: 86357 | C17: 42008 | D17: 41 | E17: 35.31 | F17: Central | G17: =VLOOKUP(D17,products[],4,0) -> Fellowes Super Stor/Drawer® Files | H17: =INDEX(Таблица3[],MATCH(формулы!F17,Таблица3[Region],0),2) -> Chris | I17: =IF(ISNUMBER(SEARCH("Xerox",G17)), "да", "нет") -> нет
B18: 91424 | C18: 42071 | D18: 41 | E18: 664.518 | F18: South | G18: =VLOOKUP(D18,products[],4,0) -> Fellowes Super Stor/Drawer® Files | H18: =INDEX(Таблица3[],MATCH(формулы!F18,Таблица3[Region],0),2) -> Sam | I18: =IF(ISNUMBER(SEARCH("Xerox",G18)), "да", "нет") -> нет
B19: 38087 | C19: 42056 | D19: 85 | E19: -76.89 | F19: West | G19: =VLOOKUP(D19,products[],4,0) -> Zoom V.92 USB External Faxmodem | H19: =INDEX(Таблица3[],MATCH(формулы!F19,Таблица3[Region],0),2) -> William | I19: =IF(ISNUMBER(SEARCH("Xerox",G19)), "да", "нет") -> нет
B20: 88360 | C20: 42056 | D20: 85 | E20: -76.89 | F20: East | G20: =VLOOKUP(D20,products[],4,0) -> Zoom V.92 USB External Faxmodem | H20: =INDEX(Таблица3[],MATCH(формулы!F20,Таблица3[Region],0),2) -> Erin | I20: =IF(ISNUMBER(SEARCH("Xerox",G20)), "да", "нет") -> нет
B21: 11206 | C21: 42183 | D21: 85 | E21: -17.03 | F21: East | G21: =VLOOKUP(D21,products[],4,0) -> Zoom V.92 USB External Faxmodem | H21: =INDEX(Таблица3[],MATCH(формулы!F21,Таблица3[Region],0),2) -> Erin | I21: =IF(ISNUMBER(SEARCH("Xerox",G21)), "да", "нет") -> нет
B22: 87587 | C22: 42183 | D22: 85 | E22: -8.515 | F22: East | G22: =VLOOKUP(D22,products[],4,0) -> Zoom V.92 USB External Faxmodem | H22: =INDEX(Таблица3[],MATCH(формулы!F22,Таблица3[Region],0),2) -> Erin | I22: =IF(ISNUMBER(SEARCH("Xerox",G22)), "да", "нет") -> нет
... B1959: 90987 | C1959: 42118 | D1959: 901 | E1959: 23.046 | F1959: West | G1959: =VLOOKUP(D1959,products[],4,0) -> DIXON Ticonderoga® Erasable Checking Pencils | H1959: =INDEX(Таблица3[],MATCH(формулы!F1959,Таблица3[Region],0),2) -> William | I1959: =IF(ISNUMBER(SEARCH("Xerox",G1959)), "да", "нет") -> нет

Sheet Orders изм.
A1: Order ID | B1: Order Date | C1: City | D1: Country | E1: Customer ID | F1: Customer Segment | G1: Discount | H1: Order Priority | I1: Postal Code | J1: Product_id | K1: Product Base Margin | L1: Product Container | M1: Profit | N1: Quantity ordered new | O1: Region | P1: Sales | Q1: Ship Date | R1: Ship Mode | S1: Shipping Cost | T1: State or Province | U1: Unit Price | V1: месяц | W1: Custom | X1: месяц (Индекс месяца) | Y1: месяц (Месяц)
A2: 86838 | B2: 42136 | C2: Prior Lake | D2: United States | E2: 14 | F2: Small Business | G2: 0.09 | H2: Medium | I2: 55372 | J2: 4 | K2: 0.43 | L2: Small Box | M2: 803.4705 | N2: 16 | O2: Central | P2: 1164.45 | Q2: 14.05.2015 | R2: Regular Air | S2: 19.99 | T2: Minnesota | U2: 78.69 | V2: 42136 | W2: Май | X2: 5 | Y2: май
A3: 91304 | B3: 42050 | C3: Coachella | D3: United States | E3: 2355 | F3: Consumer | G3: 0.1 | H3: Not Specified | I3: 92236 | J3: 4 | K3: 0.43 | L3: Small Box | M3: 465.4395 | N3: 9 | O3: West | P3: 674.55 | Q3: 16.02.2015 | R3: Regular Air | S3: 19.99 | T3: California | U3: 78.69 | V3: 42050 | W3: Февраль | X3: 2 | Y3: фев
A4: 91454 | B4: 42134 | C4: Redmond | D4: United States | E4: 43 | F4: Consumer | G4: 0 | H4: High | I4: 98052 | J4: 24 | K4: 0.52 | L4: Small Box | M4: 25.91382 | N4: 6 | O4: West | P4: 647.07 | Q4: 11.05.2015 | R4: Regular Air | S4: 19.99 | T4: Washington | U4: 99.99 | V4: 42134 | W4: Май | X4: 5 | Y4: май
A5: 87366 | B5: 42093 | C5: Cincinnati | D5: United States | E5: 84 | F5: Corporate | G5: 0.08 | H5: High | I5: 45231 | J5: 40 | K5: 0.38 | L5: Small Box | M5: 7402.32 | N5: 13 | O5: East | P5: 10728 | Q5: 02.04.2015 | R5: Regular Air | S5: 19.99 | T5: Ohio | U5: 896.99 | V5: 42093 | W5: Март | X5: 3 | Y5: мар
A6: 85826 | B6: 42012 | C6: Edmonds | D6: United States | E6: 2868 | F6: Corporate | G6: 0.03 | H6: High | I6: 98026 | J6: 40 | K6: 0.38 | L6: Small Box | M6: 3602.1312 | N6: 6 | O6: West | P6: 5220.48 | Q6: 10.01.2015 | R6: Regular Air | S6: 19.99 | T6: Washington | U6: 896.99 | V6: 42012 | W6: Январь | X6: 1 | Y6: янв
A7: 90596 | B7: 42158 | C7: Vacaville | D7: United States | E7: 87 | F7: Corporate | G7: 0.05 | H7: Low | I7: 95687 | J7: 41 | K7: 0.66 | L7: Small Box | M7: 1892.424 | N7: 19 | O7: West | P7: 3127.69 | Q7: 08.06.2015 | R7: Regular Air | S7: 19.99 | T7: California | U7: 161.55 | V7: 42158 | W7: Июнь | X7: 6 | Y7: июн
A8: 88921 | B8: 42096 | C8: Overland Park | D8: United States | E8: 197 | F8: Small Business | G8: 0 | H8: Critical | I8: 66212 | J8: 41 | K8: 0.66 | L8: Small Box | M8: 1167.158 | N8: 19 | O8: Central | P8: 3108.98 | Q8: 04.04.2015 | R8: Regular Air | S8: 19.99 | T8: Kansas | U8: 161.55 | V8: 42096 | W8: Апрель | X8: 4 | Y8: апр
A9: 51072 | B9: 42096 | C9: Detroit | D9: United States | E9: 198 | F9: Small Business | G9: 0 | H9: Critical | I9: 48138 | J9: 41 | K9: 0.66 | L9: Small Box | M9: 1014.92 | N9: 77 | O9: Central | P9: 12599.55 | Q9: 04.04.2015 | R9: Regular Air | S9: 19.99 | T9: Michigan | U9: 161.55 | V9: 42096 | W9: Апрель | X9: 4 | Y9: апр
A10: 88174 | B10: 42006 | C10: Raytown | D10: United States | E10: 674 | F10: Small Business | G10: 0.06 | H10: Critical | I10: 64133 | J10: 41 | K10: 0.66 | L10: Small Box | M10: -7.58 | N10: 3 | O10: Central | P10: 485.01 | Q10: 03.01.2015 | R10: Regular Air | S10: 19.99 | T10: Missouri | U10: 161.55 | V10: 42006 | W10: Январь | X10: 1 | Y10: янв
A11: 86357 | B11: 42008 | C11: Burleson | D11: United States | E11: 916 | F11: Corporate | G11: 0.05 | H11: Low | I11: 76028 | J11: 41 | K11: 0.66 | L11: Small Box | M11: 35.31 | N11: 3 | O11: Central | P11: 499.31 | Q11: 11.01.2015 | R11: Regular Air | S11: 19.99 | T11: Texas | U11: 161.55 | V11: 42008 | W11: Январь | X11: 1 | Y11: янв
A12: 91424 | B12: 42071 | C12: Waynesboro | D12: United States | E12: 2750 | F12: Small Business | G12: 0.02 | H12: Critical | I12: 22980 | J12: 41 | K12: 0.66 | L12: Small Box | M12: 664.518 | N12: 4 | O12: South | P12: 657.61 | Q12: 08.03.2015 | R12: Regular Air | S12: 19.99 | T12: Virginia | U12: 161.55 | V12: 42071 | W12: Март | X12: 3 | Y12: мар
A13: 38087 | B13: 42056 | C13: San Francisco | D13: United States | E13: 181 | F13: Small Business | G13: 0.02 | H13: Critical | I13: 94122 | J13: 85 | K13: 0.41 | L13: Small Box | M13: -76.89 | N13: 18 | O13: West | P13: 901.81 | Q13: 21.02.2015 | R13: Regular Air | S13: 19.99 | T13: California | U13: 49.99 | V13: 42056 | W13: Февраль | X13: 2 | Y13: фев
... A1017: 90888 | B1017: 42130 | C1017: Midland | D1017: United States | E1017: 1986 | F1017: Home Office | G1017: 0.05 | H1017: Not Specified | I1017: 79701 | J1017: 146 | K1017: 0.6 | L1017: Medium Box | M1017: 5.687 | N1017: 4 | O1017: Central | P1017: 42.99 | Q1017: 08.05.2015 | R1017: Express Air | S1017: 5.03 | T1017: Texas | U1017: 7.99 | V1017: 42130 | W1017: Май | X1017: 5 | Y1017: май
A1018: 89789 | B1018: 42068 | C1018: Berkeley | D1018: United States | E1018: 3048 | F1018: Corporate | G1018: 0.06 | H1018: High | I1018: 94704 | J1018: 148 | L1018: Large Box | M1018: 1167.38 | N1018: 10 | O1018: West | P1018: 2610.56 | Q1018: 07.03.2015 | R1018: Express Air | S1018: 24.49 | T1018: California | U1018: 276.2 | V1018: 42068 | W1018: Март | X1018: 3 | Y1018: мар
A1019: 89647 | B1019: 42138 | C1019: Glendale | D1019: United States | E1019: 353 | F1019: Home Office | G1019: 0.08 | H1019: Low | I1019: 85301 | J1019: 155 | K1019: 0.66 | L1019: Small Pack | M1019: -165.45 | N1019: 17 | O1019: West | P1019: 84.76 | Q1019: 14.05.2015 | R1019: Express Air | S1019: 4.93 | T1019: Arizona | U1019: 4.89 | V1019: 42138 | W1019: Май | X1019: 5 | Y1019: май
A1020: 90292 | B1020: 42105 | C1020: Oakland | D1020: United States | E1020: 369 | F1020: Corporate | G1020: 0.09 | H1020: Low | I1020: 94601 | J1020: 160 | K1020: 0.44 | L1020: Small Pack | M1020: 211.232 | N1020: 21 | O1020: West | P1020: 394.1 | Q1020: 13.04.2015 | R1020: Express Air | S1020: 6.15 | T1020: California | U1020: 19.23 | V1020: 42105 | W1020: Апрель | X1020: 4 | Y1020: апр
A1021: 90751 | B1021: 42055 | C1021: Kissimmee | D1021: United States | E1021: 3284 | F1021: Corporate | G1021: 0.05 | H1021: High | I1021: 34741 | J1021: 160 | K1021: 0.44 | L1021: Small Pack | M1021: -2133.278 | N1021: 6 | O1021: South | P1021: 119.78 | Q1021: 22.02.2015 | R1021: Express Air | S1021: 6.15 | T1021: Florida | U1021: 19.23 | V1021: 42055 | W1021: Февраль | X1021: 2 | Y1021: фев
A1022: 85834 | B1022: 42094 | C1022: Indian Trail | D1022: United States | E1022: 2066 | F1022: Home Office | G1022: 0.09 | H1022: Critical | I1022: 28079 | J1022: 161 | K1022: 0.58 | L1022: Medium Box | M1022: 272.694 | N1022: 2 | O1022: South | P1022: 38.98 | Q1022: 01.04.2015 | R1022: Express Air | S1022: 4.81 | T1022: North Carolina | U1022: 20.99 | V1022: 42094 | W1022: Март | X1022: 3 | Y1022: мар
A1023: 87847 | B1023: 42140 | C1023: Yuba City | D1023: United States | E1023: 1042 | F1023: Small Business | G1023: 0 | H1023: Critical | I1023: 95991 | J1023: 195 | K1023: 0.52 | L1023: Medium Box | M1023: 9.33 | N1023: 6 | O1023: West | P1023: 98.96 | Q1023: 17.05.2015 | R1023: Express Air | S1023: 6.75 | T1023: California | U1023: 14.42 | V1023: 42140 | W1023: Май | X1023: 5 | Y1023: май
A1024: 87993 | B1024: 42011 | C1024: Franklin Square | D1024: United States | E1024: 1606 | F1024: Home Office | G1024: 0.07 | H1024: Medium | I1024: 11010 | J1024: 200 | K1024: 0.41 | L1024: Large Box | M1024: -2870.2776 | N1024: 1 | O1024: East | P1024: 706.56 | Q1024: 08.01.2015 | R1024: Express Air | S1024: 24.49 | T1024: New York | U1024: 699.99 | V1024: 42011 | W1024: Январь | X1024: 1 | Y1024: янв
A1025: 87033 | B1025: 42160 | C1025: Bangor | D1025: United States | E1025: 2507 | F1025: Home Office | G1025: 0.06 | H1025: Medium | I1025: 4401 | J1025: 200 | K1025: 0.41 | L1025: Large Box | M1025: 7024.2069 | N1025: 15 | O1025: East | P1025: 10180.01 | Q1025: 07.06.2015 | R1025: Express Air | S1025: 24.49 | T1025: Maine | U1025: 699.99 | V1025: 42160 | W1025: Июнь | X1025: 6 | Y1025: июн
A1026: 88587 | B1026: 42063 | C1026: Camarillo | D1026: United States | E1026: 3355 | F1026: Corporate | G1026: 0.08 | H1026: Low | I1026: 93010 | J1026: 208 | K1026: 0.74 | L1026: Small Pack | M1026: -41.83 | N1026: 6 | O1026: West | P1026: 48.99 | Q1026: 04.03.2015 | R1026: Express Air | S1026: 2.38 | T1026: California | U1026: 8.32 | V1026: 42063 | W1026: Февраль | X1026: 2 | Y1026: фев
A1027: 89327 | B1027: 42177 | C1027: Redmond | D1027: United States | E1027: 522 | F1027: Small Business | G1027: 0.02 | H1027: Medium | I1027: 97756 | J1027: 217 | K1027: 0.38 | L1027: Medium Box | M1027: 26.1 | N1027: 3 | O1027: West | P1027: 480.37 | Q1027: 24.06.2015 | R1027: Express Air | S1027: 13.99 | T1027: Oregon | U1027: 150.98 | V1027: 42177 | W1027: Июнь | X1027: 6 | Y1027: июн
A1028: 86899 | B1028: 42030 | C1028: Saint Petersburg | D1028: United States | E1028: 3154 | F1028: Corporate | G1028: 0.08 | H1028: High | I1028: 33710 | J1028: 217 | K1028: 0.38 | L1028: Medium Box | M1028: -3.948 | N1028: 8 | O1028: South | P1028: 1183.82 | Q1028: 27.01.2015 | R1028: Express Air | S1028: 13.99 | T1028: Florida | U1028: 150.98 | V1028: 42030 | W1028: Январь | X1028: 1 | Y1028: янв
A1029: 86250 | B1029: 42169 | C1029: Morgantown | D1029: United States | E1029: 547 | F1029: Corporate | G1029: 0.03 | H1029: Not Specified | I1029: 26501 | J1029: 227 | K1029: 0.54 | L1029: Wrap Bag | M1029: 39.5853 | N1029: 4 | O1029: East | P1029: 57.37 | Q1029: 15.06.2015 | R1029: Express Air | S1029: 6.85 | T1029: West Virginia | U1029: 13.73 | V1029: 42169 | W1029: Июнь | X1029: 6 | Y1029: июн
A1030: 17155 | B1030: 42032 | C1030: Los Angeles | D1030: United States | E1030: 553 | F1030: Home Office | G1030: 0 | H1030: Medium | I1030: 90008 | J1030: 233 | K1030: 0.39 | L1030: Wrap Bag | M1030: 34.068 | N1030: 36 | O1030: West | P1030: 267.53 | Q1030: 29.01.2015 | R1030: Express Air | S1030: 2 | T1030: California | U1030: 6.88 | V1030: 42032 | W1030: Январь | X1030: 1 | Y1030: янв
... A1082: 87570 | B1082: 42053 | C1082: Durango | D1082: United States | E1082: 2141 | F1082: Home Office | G1082: 0.03 | H1082: High | I1082: 81301 | J1082: 695 | K1082: 0.59 | L1082: Small Pack | M1082: 12.5504 | N1082: 7 | O1082: West | P1082: 154.11 | Q1082: 19.02.2015 | R1082: Express Air | S1082: 5.53 | T1082: Colorado | U1082: 22.01 | V1082: 42053 | W1082: Февраль | X1082: 2 | Y1082: фев
A1083: 88028 | B1083: 42005 | C1083: Bowie | D1083: United States | E1083: 2211 | F1083: Home Office | G1083: 0.08 | H1083: Not Specified | I1083: 20715 | J1083: 712 | L1083: Large Box | M1083: -425.2084 | N1083: 2 | O1083: East | P1083: 193.88 | Q1083: 03.01.2015 | R1083: Express Air | S1083: 35 | T1083: Maryland | U1083: 95.99 | V1083: 42005 | W1083: Январь | X1083: 1 | Y1083: янв
A1084: 90110 | B1084: 42079 | C1084: Harker Heights | D1084: United States | E1084: 2272 | F1084: Corporate | G1084: 0.08 | H1084: High | I1084: 76543 | J1084: 723 | K1084: 0.56 | L1084: Small Pack | M1084: -37.6 | N1084: 5 | O1084: Central | P1084: 78.08 | Q1084: 18.03.2015 | R1084: Express Air | S1084: 7.42 | T1084: Texas | U1084: 15.73 | V1084: 42079 | W1084: Март | X1084: 3 | Y1084: мар
A1085: 89218 | B1085: 42026 | C1085: Mobile | D1085: United States | E1085: 2456 | F1085: Home Office | G1085: 0.02 | H1085: High | I1085: 36608 | J1085: 757 | K1085: 0.67 | L1085: Medium Box | M1085: -905.9904 | N1085: 11 | O1085: South | P1085: 1009.93 | Q1085: 23.01.2015 | R1085: Express Air | S1085: 39.61 | T1085: Alabama | U1085: 92.23 | V1085: 42026 | W1085: Январь | X1085: 1 | Y1085: янв
A1086: 86886 | B1086: 42016 | C1086: Costa Mesa | D1086: United States | E1086: 2490 | F1086: Home Office | G1086: 0 | H1086: Not Specified | I1086: 92627 | J1086: 767 | K1086: 0.41 | L1086: Small Pack | M1086: 82.7034 | N1086: 11 | O1086: West | P1086: 119.86 | Q1086: 14.01.2015 | R1086: Express Air | S1086: 1.99 | T1086: California | U1086: 10.01 | V1086: 42016 | W1086: Январь | X1086: 1 | Y1086: янв
A1087: 23877 | B1087: 42016 | C1087: Los Angeles | D1087: United States | E1087: 2491 | F1087: Home Office | G1087: 0 | H1087: Not Specified | I1087: 90045 | J1087: 767 | K1087: 0.41 | L1087: Small Pack | M1087: 128.03 | N1087: 42 | O1087: West | P1087: 457.63 | Q1087: 14.01.2015 | R1087: Express Air | S1087: 1.99 | T1087: California | U1087: 10.01 | V1087: 42016 | W1087: Январь | X1087: 1 | Y1087: янв
A1088: 88016 | B1088: 42082 | C1088: Brentwood | D1088: United States | E1088: 2621 | F1088: Corporate | G1088: 0.03 | H1088: High | I1088: 37027 | J1088: 787 | K1088: 0.59 | L1088: Small Pack | M1088: -177.058 | N1088: 5 | O1088: South | P1088: 207.22 | Q1088: 20.03.2015 | R1088: Express Air | S1088: 8.99 | T1088: Tennessee | U1088: 40.97 | V1088: 42082 | W1088: Март | X1088: 3 | Y1088: мар
A1089: 90103 | B1089: 42121 | C1089: Jackson | D1089: United States | E1089: 3320 | F1089: Small Business | G1089: 0.09 | H1089: Not Specified | I1089: 38301 | J1089: 787 | K1089: 0.59 | L1089: Small Pack | M1089: 66.216 | N1089: 22 | O1089: South | P1089: 824.7 | Q1089: 29.04.2015 | R1089: Express Air | S1089: 8.99 | T1089: Tennessee | U1089: 40.97 | V1089: 42121 | W1089: Апрель | X1089: 4 | Y1089: апр
A1090: 86633 | B1090: 42171 | C1090: Winchester | D1090: United States | E1090: 2677 | F1090: Small Business | G1090: 0.03 | H1090: Critical | I1090: 22601 | J1090: 799 | K1090: 0.76 | L1090: Medium Box | M1090: -32.816 | N1090: 10 | O1090: South | P1090: 419.27 | Q1090: 17.06.2015 | R1090: Express Air | S1090: 58.66 | T1090: Virginia | U1090: 41.32 | V1090: 42171 | W1090: Июнь | X1090: 6 | Y1090: июн
A1091: 88611 | B1091: 42131 | C1091: Louisville | D1091: United States | E1091: 2962 | F1091: Consumer | G1091: 0.07 | H1091: High | I1091: 80027 | J1091: 818 | K1091: 0.39 | L1091: Wrap Bag | M1091: 33.3477 | N1091: 10 | O1091: West | P1091: 48.33 | Q1091: 09.05.2015 | R1091: Express Air | S1091: 0.88 | T1091: Colorado | U1091: 4.76 | V1091: 42131 | W1091: Май | X1091: 5 | Y1091: май
A1092: 89743 | B1092: 42156 | C1092: Newark | D1092: United States | E1092: 2817 | F1092: Corporate | G1092: 0.04 | H1092: High | I1092: 43055 | J1092: 825 | K1092: 0.35 | L1092: Small Pack | M1092: -18.3216 | N1092: 3 | O1092: East | P1092: 147.56 | Q1092: 02.06.2015 | R1092: Express Air | S1092: 1.25 | T1092: Ohio | U1092: 55.99 | V1092: 42156 | W1092: Июнь | X1092: 6 | Y1092: июн
A1093: 90296 | B1093: 42180 | C1093: Adrian | D1093: United States | E1093: 3261 | F1093: Consumer | G1093: 0.07 | H1093: Not Specified | I1093: 49221 | J1093: 829 | K1093: 0.61 | L1093: Large Box | M1093: 710.6724 | N1093: 10 | O1093: Central | P1093: 1029.96 | Q1093: 26.06.2015 | R1093: Express Air | S1093: 24.49 | T1093: Michigan | U1093: 105.34 | V1093: 42180 | W1093: Июнь | X1093: 6 | Y1093: июн
A1094: 88839 | B1094: 42119 | C1094: Kennesaw | D1094: United States | E1094: 3379 | F1094: Home Office | G1094: 0.05 | H1094: Critical | I1094: 30144 | J1094: 840 | K1094: 0.84 | L1094: Wrap Bag | M1094: 1628.37 | N1094: 18 | O1094: South | P1094: 59.22 | Q1094: 26.04.2015 | R1094: Express Air | S1094: 1.92 | T1094: Georgia | U1094: 3.14 | V1094: 42119 | W1094: Апрель | X1094: 4 | Y1094: апр
A1095: 48483 | B1095: 42165 | C1095: Philadelphia | D1095: United States | E1095: 3079 | F1095: Small Business | G1095: 0 | H1095: Critical | I1095: 19112 | J1095: 863 | K1095: 0.38 | L1095: Wrap Bag | M1095: 10.01 | N1095: 33 | O1095: East | P1095: 87.18 | Q1095: 11.06.2015 | R1095: Express Air | S1095: 1 | T1095: Pennsylvania | U1095: 2.21 | V1095: 42165 | W1095: Июнь | X1095: 6 | Y1095: июн
... A1298: 89909 | B1298: 42010 | C1298: Hilton Head Island | D1298: United States | E1298: 799 | F1298: Consumer | G1298: 0.01 | H1298: Not Specified | I1298: 29915 | J1298: 336 | K1298: 0.74 | L1298: Jumbo Drum | M1298: 131.382 | N1298: 6 | O1298: South | P1298: 958.46 | Q1298: 08.01.2015 | R1298: Delivery Truck | S1298: 30 | T1298: South Carolina | U1298: 150.98 | V1298: 42010 | W1298: Январь | X1298: 1 | Y1298: янв
A1299: 91195 | B1299: 42069 | C1299: Shoreview | D1299: United States | E1299: 868 | F1299: Corporate | G1299: 0.09 | H1299: Critical | I1299: 55126 | J1299: 357 | L1299: Jumbo Drum | M1299: -2946.051 | N1299: 12 | O1299: Central | P1299: 3918.98 | Q1299: 07.03.2015 | R1299: Delivery Truck | S1299: 60 | T1299: Minnesota | U1299: 349.45 | V1299: 42069 | W1299: Март | X1299: 3 | Y1299: мар
A1300: 89787 | B1300: 42103 | C1300: Altamonte Springs | D1300: United States | E1300: 1178 | F1300: Consumer | G1300: 0.09 | H1300: High | I1300: 32701 | J1300: 357 | L1300: Jumbo Drum | M1300: -369.11 | N1300: 7 | O1300: South | P1300: 2307.26 | Q1300: 10.04.2015 | R1300: Delivery Truck | S1300: 60 | T1300: Florida | U1300: 349.45 | V1300: 42103 | W1300: Апрель | X1300: 4 | Y1300: апр
A1301: 85867 | B1301: 42127 | C1301: Goldsboro | D1301: United States | E1301: 1739 | F1301: Corporate | G1301: 0.09 | H1301: High | I1301: 27534 | J1301: 357 | L1301: Jumbo Drum | M1301: -90.748 | N1301: 17 | O1301: South | P1301: 5835.41 | Q1301: 04.05.2015 | R1301: Delivery Truck | S1301: 60 | T1301: North Carolina | U1301: 349.45 | V1301: 42127 | W1301: Май | X1301: 5 | Y1301: май
A1302: 86432 | B1302: 42185 | C1302: Orlando | D1302: United States | E1302: 3119 | F1302: Corporate | G1302: 0.08 | H1302: Critical | I1302: 32839 | J1302: 357 | L1302: Jumbo Drum | M1302: 513.084 | N1302: 11 | O1302: South | P1302: 3772.19 | Q1302: 02.07.2015 | R1302: Delivery Truck | S1302: 60 | T1302: Florida | U1302: 349.45 | V1302: 42185 | W1302: Июнь | X1302: 6 | Y1302: июн
A1303: 88825 | B1303: 42150 | C1303: Longview | D1303: United States | E1303: 3257 | F1303: Consumer | G1303: 0.01 | H1303: Not Specified | I1303: 98632 | J1303: 357 | L1303: Jumbo Drum | M1303: 3739.3929 | N1303: 15 | O1303: West | P1303: 5419.41 | Q1303: 27.05.2015 | R1303: Delivery Truck | S1303: 60 | T1303: Washington | U1303: 349.45 | V1303: 42150 | W1303: Май | X1303: 5 | Y1303: май
A1304: 89537 | B1304: 42148 | C1304: Amarillo | D1304: United States | E1304: 885 | F1304: Corporate | G1304: 0.06 | H1304: Critical | I1304: 79109 | J1304: 362 | K1304: 0.6 | L1304: Jumbo Drum | M1304: 55.888 | N1304: 41 | O1304: Central | P1304: 1033.56 | Q1304: 25.05.2015 | R1304: Delivery Truck | S1304: 14.36 | T1304: Texas | U1304: 25.98 | V1304: 42148 | W1304: Май | X1304: 5 | Y1304: май
A1305: 86899 | B1305: 42030 | C1305: Sanford | D1305: United States | E1305: 3155 | F1305: Corporate | G1305: 0.03 | H1305: High | I1305: 32771 | J1305: 362 | K1305: 0.6 | L1305: Jumbo Drum | M1305: 57.546 | N1305: 4 | O1305: South | P1305: 107.66 | Q1305: 27.01.2015 | R1305: Delivery Truck | S1305: 14.36 | T1305: Florida | U1305: 25.98 | V1305: 42030 | W1305: Январь | X1305: 1 | Y1305: янв
A1306: 86051 | B1306: 42039 | C1306: Burnsville | D1306: United States | E1306: 2204 | F1306: Home Office | G1306: 0.07 | H1306: Low | I1306: 55337 | J1306: 363 | K1306: 0.58 | L1306: Jumbo Drum | M1306: -157.56 | N1306: 5 | O1306: Central | P1306: 169.46 | Q1306: 08.02.2015 | R1306: Delivery Truck | S1306: 19.19 | T1306: Minnesota | U1306: 33.94 | V1306: 42039 | W1306: Февраль | X1306: 2 | Y1306: фев
A1307: 33635 | B1307: 42016 | C1307: New York City | D1307: United States | E1307: 898 | F1307: Small Business | G1307: 0.04 | H1307: High | I1307: 10039 | J1307: 369 | K1307: 0.38 | L1307: Jumbo Drum | M1307: -173.0952 | N1307: 6 | O1307: East | P1307: 573.31 | Q1307: 13.01.2015 | R1307: Delivery Truck | S1307: 28 | T1307: New York | U1307: 90.97 | V1307: 42016 | W1307: Январь | X1307: 1 | Y1307: янв
A1308: 86263 | B1308: 42016 | C1308: Altoona | D1308: United States | E1308: 899 | F1308: Small Business | G1308: 0.04 | H1308: High | I1308: 16602 | J1308: 369 | K1308: 0.38 | L1308: Jumbo Drum | M1308: -173.0952 | N1308: 2 | O1308: East | P1308: 191.1 | Q1308: 13.01.2015 | R1308: Delivery Truck | S1308: 28 | T1308: Pennsylvania | U1308: 90.97 | V1308: 42016 | W1308: Январь | X1308: 1 | Y1308: янв
A1309: 89084 | B1309: 42085 | C1309: Prior Lake | D1309: United States | E1309: 950 | F1309: Consumer | G1309: 0.05 | H1309: Low | I1309: 55372 | J1309: 387 | K1309: 0.57 | L1309: Jumbo Drum | M1309: -2561.3235 | N1309: 1 | O1309: Central | P1309: 1497.22 | Q1309: 22.03.2015 | R1309: Delivery Truck | S1309: 29.7 | T1309: Minnesota | U1309: 1500.97 | V1309: 42085 | W1309: Март | X1309: 3 | Y1309: мар
A1310: 91581 | B1310: 42085 | C1310: Burleson | D1310: United States | E1310: 959 | F1310: Corporate | G1310: 0.01 | H1310: Not Specified | I1310: 76028 | J1310: 391 | K1310: 0.56 | L1310: Jumbo Drum | M1310: 837.6807 | N1310: 8 | O1310: Central | P1310: 1214.03 | Q1310: 23.03.2015 | R1310: Delivery Truck | S1310: 17.85 | T1310: Texas | U1310: 145.45 | V1310: 42085 | W1310: Март | X1310: 3 | Y1310: мар
A1311: 86051 | B1311: 42039 | C1311: Brooklyn Park | D1311: United States | E1311: 2203 | F1311: Home Office | G1311: 0.08 | H1311: Low | I1311: 55445 | J1311: 391 | K1311: 0.56 | L1311: Jumbo Drum | M1311: 751.58 | N1311: 8 | O1311: Central | P1311: 1117.66 | Q1311: 04.02.2015 | R1311: Delivery Truck | S1311: 17.85 | T1311: Minnesota | U1311: 145.45 | V1311: 42039 | W1311: Февраль | X1311: 2 | Y1311: фев
A1312: 85914 | B1312: 42009 | C1312: Norman | D1312: United States | E1312: 2630 | F1312: Small Business | G1312: 0 | H1312: Critical | I1312: 73071 | J1312: 391 | K1312: 0.56 | L1312: Jumbo Drum | M1312: 801.7468 | N1312: 8 | O1312: Central | P1312: 1191.2 | Q1312: 07.01.2015 | R1312: Delivery Truck | S1312: 17.85 | T1312: Oklahoma | U1312: 145.45 | V1312: 42009 | W1312: Январь | X1312: 1 | Y1312: янв
A1313: 87259 | B1313: 42063 | C1313: Riverside | D1313: United States | E1313: 972 | F1313: Corporate | G1313: 0.03 | H1313: Low | I1313: 92503 | J1313: 392 | K1313: 0.6 | L1313: Jumbo Drum | M1313: -116.584 | N1313: 2 | O1313: West | P1313: 619.38 | Q1313: 05.03.2015 | R1313: Delivery Truck | S1313: 69.55 | T1313: California | U1313: 284.98 | V1313: 42063 | W1313: Февраль | X1313: 2 | Y1313: фев
A1314: 86723 | B1314: 42162 | C1314: Charlottesville | D1314: United States | E1314: 1672 | F1314: Small Business | G1314: 0.02 | H1314: Low | I1314: 22901 | J1314: 392 | K1314: 0.6 | L1314: Jumbo Drum | M1314: 15.528 | N1314: 3 | O1314: South | P1314: 926.3 | Q1314: 12.06.2015 | R1314: Delivery Truck | S1314: 69.55 | T1314: Virginia | U1314: 284.98 | V1314: 42162 | W1314: Июнь | X1314: 6 | Y1314: июн
A1315: 89631 | B1315: 42090 | C1315: Bethlehem | D1315: United States | E1315: 1072 | F1315: Corporate | G1315: 0.01 | H1315: Not Specified | I1315: 18018 | J1315: 434 | K1315: 0.77 | L1315: Jumbo Drum | M1315: -505.76 | N1315: 3 | O1315: East | P1315: 473.53 | Q1315: 30.03.2015 | R1315: Delivery Truck | S1315: 60.2 | T1315: Pennsylvania | U1315: 150.89 | V1315: 42090 | W1315: Март | X1315: 3 | Y1315: мар
... A1383: 87071 | B1383: 42010 | C1383: Fairfax | D1383: United States | E1383: 2146 | F1383: Corporate | G1383: 0.05 | H1383: Low | I1383: 20151 | J1383: 127 | K1383: 0.84 | L1383: Large Box | M1383: 52.776 | N1383: 2 | O1383: South | P1383: 53.02 | Q1383: 10.01.2015 | R1383: Regular Air | S1383: 35 | T1383: Virginia | U1383: 20.34 | V1383: 42010 | W1383: Январь | X1383: 1 | Y1383: янв
A1384: 87277 | B1384: 42128 | C1384: Medford | D1384: United States | E1384: 335 | F1384: Corporate | G1384: 0.06 | H1384: Critical | I1384: 97504 | J1384: 148 | L1384: Large Box | M1384: 2639.4708 | N1384: 14 | O1384: West | P1384: 3825.32 | Q1384: 05.05.2015 | R1384: Regular Air | S1384: 24.49 | T1384: Oregon | U1384: 276.2 | V1384: 42128 | W1384: Май | X1384: 5 | Y1384: май
A1385: 88838 | B1385: 42114 | C1385: La Grange | D1385: United States | E1385: 3380 | F1385: Home Office | G1385: 0.09 | H1385: Critical | I1385: 30240 | J1385: 148 | L1385: Large Box | M1385: 3193.284 | N1385: 11 | O1385: South | P1385: 2941.42 | Q1385: 21.04.2015 | R1385: Regular Air | S1385: 24.49 | T1385: Georgia | U1385: 276.2 | V1385: 42114 | W1385: Апрель | X1385: 4 | Y1385: апр
A1386: 86383 | B1386: 42068 | C1386: Clayton | D1386: United States | E1386: 392 | F1386: Corporate | G1386: 0.01 | H1386: Medium | I1386: 63105 | J1386: 173 | K1386: 0.6 | L1386: Large Box | M1386: 27.91 | N1386: 2 | O1386: Central | P1386: 43.65 | Q1386: 08.03.2015 | R1386: Regular Air | S1386: 11.17 | T1386: Missouri | U1386: 19.99 | V1386: 42068 | W1386: Март | X1386: 3 | Y1386: мар
A1387: 89942 | B1387: 42096 | C1387: Valparaiso | D1387: United States | E1387: 1777 | F1387: Corporate | G1387: 0.03 | H1387: Not Specified | I1387: 46383 | J1387: 173 | K1387: 0.6 | L1387: Large Box | M1387: -20.8764 | N1387: 12 | O1387: Central | P1387: 251.61 | Q1387: 03.04.2015 | R1387: Regular Air | S1387: 11.17 | T1387: Indiana | U1387: 19.99 | V1387: 42096 | W1387: Апрель | X1387: 4 | Y1387: апр
A1388: 89716 | B1388: 42018 | C1388: Post Falls | D1388: United States | E1388: 3148 | F1388: Corporate | G1388: 0.06 | H1388: Medium | I1388: 83854 | J1388: 173 | K1388: 0.6 | L1388: Large Box | M1388: -66.8236 | N1388: 7 | O1388: West | P1388: 139.49 | Q1388: 14.01.2015 | R1388: Regular Air | S1388: 11.17 | T1388: Idaho | U1388: 19.99 | V1388: 42018 | W1388: Январь | X1388: 1 | Y1388: янв
A1389: 88060 | B1389: 42015 | C1389: Beverly | D1389: United States | E1389: 467 | F1389: Small Business | G1389: 0.02 | H1389: Not Specified | I1389: 1915 | J1389: 194 | K1389: 0.73 | L1389: Large Box | M1389: -556.8096 | N1389: 11 | O1389: East | P1389: 143.63 | Q1389: 12.01.2015 | R1389: Regular Air | S1389: 14.37 | T1389: Massachusetts | U1389: 12.99 | V1389: 42015 | W1389: Январь | X1389: 1 | Y1389: янв
A1390: 87259 | B1390: 42063 | C1390: Riverside | D1390: United States | E1390: 972 | F1390: Corporate | G1390: 0 | H1390: Low | I1390: 92503 | J1390: 194 | K1390: 0.73 | L1390: Large Box | M1390: 12.8961 | N1390: 1 | O1390: West | P1390: 18.69 | Q1390: 28.02.2015 | R1390: Regular Air | S1390: 14.37 | T1390: California | U1390: 12.99 | V1390: 42063 | W1390: Февраль | X1390: 2 | Y1390: фев
A1391: 89129 | B1391: 42020 | C1391: Mandan | D1391: United States | E1391: 3036 | F1391: Home Office | G1391: 0.02 | H1391: Not Specified | I1391: 58554 | J1391: 194 | K1391: 0.73 | L1391: Large Box | M1391: -159.86 | N1391: 5 | O1391: Central | P1391: 67.64 | Q1391: 18.01.2015 | R1391: Regular Air | S1391: 14.37 | T1391: North Dakota | U1391: 12.99 | V1391: 42020 | W1391: Январь | X1391: 1 | Y1391: янв
A1392: 90354 | B1392: 42117 | C1392: Oswego | D1392: United States | E1392: 483 | F1392: Corporate | G1392: 0.07 | H1392: Not Specified | I1392: 60543 | J1392: 200 | K1392: 0.41 | L1392: Large Box | M1392: 2583.5615 | N1392: 9 | O1392: Central | P1392: 5976.09 | Q1392: 25.04.2015 | R1392: Regular Air | S1392: 24.49 | T1392: Illinois | U1392: 699.99 | V1392: 42117 | W1392: Апрель | X1392: 4 | Y1392: апр
A1393: 86899 | B1393: 42030 | C1393: Sanford | D1393: United States | E1393: 3155 | F1393: Corporate | G1393: 0.1 | H1393: High | I1393: 32771 | J1393: 234 | K1393: 0.81 | L1393: Large Box | M1393: -333.4254 | N1393: 10 | O1393: South | P1393: 318.83 | Q1393: 27.01.2015 | R1393: Regular Air | S1393: 35 | T1393: Florida | U1393: 32.48 | V1393: 42030 | W1393: Январь | X1393: 1 | Y1393: янв
A1394: 88645 | B1394: 42017 | C1394: Pomona | D1394: United States | E1394: 576 | F1394: Corporate | G1394: 0.06 | H1394: Low | I1394: 91767 | J1394: 239 | K1394: 0.6 | L1394: Large Box | M1394: -566 | N1394: 4 | O1394: West | P1394: 32.6 | Q1394: 17.01.2015 | R1394: Regular Air | S1394: 49 | T1394: California | U1394: 4.48 | V1394: 42017 | W1394: Январь | X1394: 1 | Y1394: янв
A1395: 89787 | B1395: 42103 | C1395: Altamonte Springs | D1395: United States | E1395: 1178 | F1395: Consumer | G1395: 0.03 | H1395: High | I1395: 32701 | J1395: 239 | K1395: 0.6 | L1395: Large Box | M1395: 64.266 | N1395: 2 | O1395: South | P1395: 21.46 | Q1395: 11.04.2015 | R1395: Regular Air | S1395: 49 | T1395: Florida | U1395: 4.48 | V1395: 42103 | W1395: Апрель | X1395: 4 | Y1395: апр
A1396: 90861 | B1396: 42126 | C1396: Irving | D1396: United States | E1396: 2426 | F1396: Small Business | G1396: 0.08 | H1396: Low | I1396: 75061 | J1396: 239 | K1396: 0.6 | L1396: Large Box | M1396: 139.5801 | N1396: 37 | O1396: Central | P1396: 202.29 | Q1396: 02.05.2015 | R1396: Regular Air | S1396: 49 | T1396: Texas | U1396: 4.48 | V1396: 42126 | W1396: Май | X1396: 5 | Y1396: май
A1397: 88503 | B1397: 42140 | C1397: Saint Louis | D1397: United States | E1397: 688 | F1397: Small Business | G1397: 0.07 | H1397: Critical | I1397: 63116 | J1397: 285 | K1397: 0.8 | L1397: Large Box | M1397: -207.28 | N1397: 10 | O1397: Central | P1397: 2716.09 | Q1397: 16.05.2015 | R1397: Regular Air | S1397: 35 | T1397: Missouri | U1397: 279.48 | V1397: 42140 | W1397: Май | X1397: 5 | Y1397: май
... A1425: 87603 | B1425: 42009 | C1425: Commerce City | D1425: United States | E1425: 1316 | F1425: Home Office | G1425: 0.05 | H1425: Low | I1425: 80022 | J1425: 485 | K1425: 0.81 | L1425: Large Box | M1425: -746.44 | N1425: 8 | O1425: West | P1425: 637.76 | Q1425: 09.01.2015 | R1425: Regular Air | S1425: 35 | T1425: Colorado | U1425: 80.98 | V1425: 42009 | W1425: Январь | X1425: 1 | Y1425: янв
A1426: 89112 | B1426: 42028 | C1426: Vincennes | D1426: United States | E1426: 1281 | F1426: Small Business | G1426: 0.1 | H1426: Low | I1426: 47591 | J1426: 495 | L1426: Large Box | M1426: 875.2844 | N1426: 8 | O1426: Central | P1426: 1774.5 | Q1426: 26.01.2015 | R1426: Regular Air | S1426: 24.49 | T1426: Indiana | U1426: 238.4 | V1426: 42028 | W1426: Январь | X1426: 1 | Y1426: янв
A1427: 29319 | B1427: 42028 | C1427: Philadelphia | D1427: United States | E1427: 1282 | F1427: Small Business | G1427: 0.1 | H1427: Low | I1427: 19134 | J1427: 495 | L1427: Large Box | M1427: 460.676 | N1427: 30 | O1427: East | P1427: 6654.39 | Q1427: 26.01.2015 | R1427: Regular Air | S1427: 24.49 | T1427: Pennsylvania | U1427: 238.4 | V1427: 42028 | W1427: Январь | X1427: 1 | Y1427: янв
A1428: 91116 | B1428: 42167 | C1428: Clearfield | D1428: United States | E1428: 1469 | F1428: Small Business | G1428: 0.04 | H1428: Low | I1428: 84015 | J1428: 534 | K1428: 0.79 | L1428: Large Box | M1428: 589.188 | N1428: 9 | O1428: West | P1428: 940.64 | Q1428: 16.06.2015 | R1428: Regular Air | S1428: 10.12 | T1428: Utah | U1428: 105.29 | V1428: 42167 | W1428: Июнь | X1428: 6 | Y1428: июн
A1429: 86951 | B1429: 42008 | C1429: Roswell | D1429: United States | E1429: 2393 | F1429: Corporate | G1429: 0.06 | H1429: High | I1429: 30076 | J1429: 534 | K1429: 0.79 | L1429: Large Box | M1429: -45.01 | N1429: 12 | O1429: South | P1429: 1202.66 | Q1429: 06.01.2015 | R1429: Regular Air | S1429: 10.12 | T1429: Georgia | U1429: 105.29 | V1429: 42008 | W1429: Январь | X1429: 1 | Y1429: янв
A1430: 88487 | B1430: 42178 | C1430: Richmond | D1430: United States | E1430: 1548 | F1430: Corporate | G1430: 0 | H1430: Low | I1430: 47374 | J1430: 552 | K1430: 0.44 | L1430: Large Box | M1430: -367.165 | N1430: 18 | O1430: Central | P1430: 11015.82 | Q1430: 25.06.2015 | R1430: Regular Air | S1430: 24.49 | T1430: Indiana | U1430: 599.99 | V1430: 42178 | W1430: Июнь | X1430: 6 | Y1430: июн
A1431: 87426 | B1431: 42088 | C1431: Annandale | D1431: United States | E1431: 1557 | F1431: Consumer | G1431: 0.09 | H1431: Low | I1431: 22003 | J1431: 558 | K1431: 0.59 | L1431: Large Box | M1431: -954.758 | N1431: 15 | O1431: South | P1431: 879.62 | Q1431: 02.04.2015 | R1431: Regular Air | S1431: 49 | T1431: Virginia | U1431: 60.98 | V1431: 42088 | W1431: Март | X1431: 3 | Y1431: мар
A1432: 3841 | B1432: 42098 | C1432: Washington | D1432: United States | E1432: 1733 | F1432: Small Business | G1432: 0.02 | H1432: Not Specified | I1432: 20012 | J1432: 558 | K1432: 0.59 | L1432: Large Box | M1432: -662.52 | N1432: 34 | O1432: East | P1432: 2119.54 | Q1432: 06.04.2015 | R1432: Regular Air | S1432: 49 | T1432: District of Columbia | U1432: 60.98 | V1432: 42098 | W1432: Апрель | X1432: 4 | Y1432: апр
A1433: 88443 | B1433: 42098 | C1433: Harrison | D1433: United States | E1433: 1734 | F1433: Small Business | G1433: 0.02 | H1433: Not Specified | I1433: 10528 | J1433: 558 | K1433: 0.59 | L1433: Large Box | M1433: -596.268 | N1433: 9 | O1433: East | P1433: 561.06 | Q1433: 06.04.2015 | R1433: Regular Air | S1433: 49 | T1433: New York | U1433: 60.98 | V1433: 42098 | W1433: Апрель | X1433: 4 | Y1433: апр
A1434: 89106 | B1434: 42069 | C1434: Freeport | D1434: United States | E1434: 1771 | F1434: Home Office | G1434: 0.07 | H1434: Medium | I1434: 61032 | J1434: 558 | K1434: 0.59 | L1434: Large Box | M1434: -807.89 | N1434: 7 | O1434: Central | P1434: 410.17 | Q1434: 07.03.2015 | R1434: Regular Air | S1434: 49 | T1434: Illinois | U1434: 60.98 | V1434: 42069 | W1434: Март | X1434: 3 | Y1434: мар
A1435: 90601 | B1435: 42051 | C1435: Glen Cove | D1435: United States | E1435: 1625 | F1435: Home Office | G1435: 0 | H1435: Medium | I1435: 11542 | J1435: 576 | K1435: 0.79 | L1435: Large Box | M1435: -263.11193 | N1435: 11 | O1435: East | P1435: 1959.88 | Q1435: 18.02.2015 | R1435: Regular Air | S1435: 69 | T1435: New York | U1435: 209.37 | V1435: 42051 | W1435: Февраль | X1435: 2 | Y1435: фев
A1436: 90011 | B1436: 42058 | C1436: Livonia | D1436: United States | E1436: 2892 | F1436: Consumer | G1436: 0.1 | H1436: High | I1436: 48154 | J1436: 576 | K1436: 0.79 | L1436: Large Box | M1436: -165.59492 | N1436: 11 | O1436: Central | P1436: 2125.12 | Q1436: 25.02.2015 | R1436: Regular Air | S1436: 69 | T1436: Michigan | U1436: 209.37 | V1436: 42058 | W1436: Февраль | X1436: 2 | Y1436: фев
A1437: 86645 | B1437: 42127 | C1437: Fairfield | D1437: United States | E1437: 1680 | F1437: Consumer | G1437: 0.03 | H1437: Low | I1437: 45014 | J1437: 593 | K1437: 0.57 | L1437: Large Box | M1437: 554.77 | N1437: 17 | O1437: East | P1437: 817.32 | Q1437: 05.05.2015 | R1437: Regular Air | S1437: 10.25 | T1437: Ohio | U1437: 49.34 | V1437: 42127 | W1437: Май | X1437: 5 | Y1437: май
A1438: 91077 | B1438: 42087 | C1438: Highland | D1438: United States | E1438: 1689 | F1438: Corporate | G1438: 0 | H1438: High | I1438: 46322 | J1438: 596 | K1438: 0.83 | L1438: Large Box | M1438: -628.38 | N1438: 10 | O1438: Central | P1438: 514.79 | Q1438: 25.03.2015 | R1438: Regular Air | S1438: 35 | T1438: Indiana | U1438: 48.91 | V1438: 42087 | W1438: Март | X1438: 3 | Y1438: мар
A1439: 90631 | B1439: 42111 | C1439: Kettering | D1439: United States | E1439: 1889 | F1439: Home Office | G1439: 0.09 | H1439: Low | I1439: 45429 | J1439: 638 | K1439: 0.83 | L1439: Large Box | M1439: -1025.0172 | N1439: 14 | O1439: East | P1439: 1059.38 | Q1439: 21.04.2015 | R1439: Regular Air | S1439: 35 | T1439: Ohio | U1439: 78.8 | V1439: 42111 | W1439: Апрель | X1439: 4 | Y1439: апр
... A1444: 86054 | B1444: 42088 | C1444: Bloomington | D1444: United States | E1444: 2201 | F1444: Small Business | G1444: 0.17 | H1444: Critical | I1444: 55420 | J1444: 710 | K1444: 0.58 | L1444: Large Box | M1444: -9.13 | N1444: 1 | O1444: Central | P1444: 27.96 | Q1444: 27.03.2015 | R1444: Regular Air | S1444: 13.56 | T1444: Minnesota | U1444: 14.89 | V1444: 42088 | W1444: Март | X1444: 3 | Y1444: мар
A1445: 90154 | B1445: 42135 | C1445: Fairfield | D1445: United States | E1445: 3388 | F1445: Corporate | G1445: 0.03 | H1445: Not Specified | I1445: 94533 | J1445: 712 | L1445: Large Box | M1445: 67.012 | N1445: 9 | O1445: West | P1445: 894.64 | Q1445: 12.05.2015 | R1445: Regular Air | S1445: 35 | T1445: California | U1445: 95.99 | V1445: 42135 | W1445: Май | X1445: 5 | Y1445: май
A1446: 86166 | B1446: 42178 | C1446: Cumberland | D1446: United States | E1446: 2352 | F1446: Home Office | G1446: 0.09 | H1446: Not Specified | I1446: 21501 | J1446: 738 | K1446: 0.68 | L1446: Large Box | M1446: -1537.1356 | N1446: 19 | O1446: East | P1446: 1302.98 | Q1446: 24.06.2015 | R1446: Regular Air | S1446: 69 | T1446: Maryland | U1446: 71.37 | V1446: 42178 | W1446: Июнь | X1446: 6 | Y1446: июн
A1447: 91414 | B1447: 42041 | C1447: Statesboro | D1447: United States | E1447: 2486 | F1447: Small Business | G1447: 0.02 | H1447: High | I1447: 30458 | J1447: 738 | K1447: 0.68 | L1447: Large Box | M1447: -439.908 | N1447: 4 | O1447: South | P1447: 237.62 | Q1447: 07.02.2015 | R1447: Regular Air | S1447: 69 | T1447: Georgia | U1447: 71.37 | V1447: 42041 | W1447: Февраль | X1447: 2 | Y1447: фев
A1448: 86753 | B1448: 42014 | C1448: Petersburg | D1448: United States | E1448: 2418 | F1448: Consumer | G1448: 0.1 | H1448: High | I1448: 23805 | J1448: 748 | K1448: 0.5 | L1448: Large Box | M1448: -343.126 | N1448: 11 | O1448: South | P1448: 6355.69 | Q1448: 11.01.2015 | R1448: Regular Air | S1448: 24.49 | T1448: Virginia | U1448: 599.99 | V1448: 42014 | W1448: Январь | X1448: 1 | Y1448: янв
A1449: 86486 | B1449: 42059 | C1449: Gorham | D1449: United States | E1449: 2660 | F1449: Small Business | G1449: 0.01 | H1449: Critical | I1449: 4038 | J1449: 793 | L1449: Large Box | M1449: -321.51 | N1449: 4 | O1449: East | P1449: 599.03 | Q1449: 26.02.2015 | R1449: Regular Air | S1449: 35 | T1449: Maine | U1449: 138.14 | V1449: 42059 | W1449: Февраль | X1449: 2 | Y1449: фев
A1450: 87316 | B1450: 42025 | C1450: Des Moines | D1450: United States | E1450: 2855 | F1450: Corporate | G1450: 0.03 | H1450: Medium | I1450: 98198 | J1450: 829 | K1450: 0.61 | L1450: Large Box | M1450: 618.1308 | N1450: 10 | O1450: West | P1450: 1038.14 | Q1450: 22.01.2015 | R1450: Regular Air | S1450: 24.49 | T1450: Washington | U1450: 105.34 | V1450: 42025 | W1450: Январь | X1450: 1 | Y1450: янв
A1451: 55300 | B1451: 42055 | C1451: Charlotte | D1451: United States | E1451: 2882 | F1451: Consumer | G1451: 0.02 | H1451: High | I1451: 28206 | J1451: 835 | K1451: 0.6 | L1451: Large Box | M1451: -307.2965 | N1451: 31 | O1451: South | P1451: 350.48 | Q1451: 22.02.2015 | R1451: Regular Air | S1451: 13.04 | T1451: North Carolina | U1451: 10.68 | V1451: 42055 | W1451: Февраль | X1451: 2 | Y1451: фев
A1452: 87630 | B1452: 42055 | C1452: Parma | D1452: United States | E1452: 2886 | F1452: Consumer | G1452: 0.02 | H1452: High | I1452: 44134 | J1452: 835 | K1452: 0.6 | L1452: Large Box | M1452: -231.05 | N1452: 8 | O1452: East | P1452: 90.45 | Q1452: 22.02.2015 | R1452: Regular Air | S1452: 13.04 | T1452: Ohio | U1452: 10.68 | V1452: 42055 | W1452: Февраль | X1452: 2 | Y1452: фев
A1453: 7623 | B1453: 42122 | C1453: Boston | D1453: United States | E1453: 3011 | F1453: Corporate | G1453: 0.03 | H1453: Critical | I1453: 2113 | J1453: 851 | K1453: 0.52 | L1453: Large Box | M1453: 1282.496 | N1453: 32 | O1453: East | P1453: 9705.46 | Q1453: 30.04.2015 | R1453: Regular Air | S1453: 24.49 | T1453: Massachusetts | U1453: 300.65 | V1453: 42122 | W1453: Апрель | X1453: 4 | Y1453: апр
A1454: 86346 | B1454: 42122 | C1454: Rochester | D1454: United States | E1454: 3012 | F1454: Corporate | G1454: 0.03 | H1454: Critical | I1454: 14609 | J1454: 851 | K1454: 0.52 | L1454: Large Box | M1454: 1474.8704 | N1454: 8 | O1454: East | P1454: 2426.36 | Q1454: 30.04.2015 | R1454: Regular Air | S1454: 24.49 | T1454: New York | U1454: 300.65 | V1454: 42122 | W1454: Апрель | X1454: 4 | Y1454: апр
...

Sheet abc анализ
C2: Названия строк | D2: Выручка | E2: Выручка % от общего | F2: Выручка нарастающий % | G2: Группа ABC
C3: Office Machines | D3: 318169.68 | E3: 0.16533982 | F3: 0.16533982 | G3: =IF(F3 <= 80%, "A", IF(F3 <= 95%, "B", "C")) -> A | I3: группа | J3: A | K3: B | L3: C
C4: Chairs & Chairmats | D4: 261072.73 | E4: 0.13566886 | F4: 0.30100868 | G4: =IF(F4 <= 80%, "A", IF(F4 <= 95%, "B", "C")) -> A | I4: процент группы | J4: =COUNTIF($G$3:$G$19, J3) / COUNT($F$3:$G$19) -> 0.41176471 | K4: =COUNTIF($G$3:$G$19, K3) / COUNT($F$3:$G$19) -> 0.23529412 | L4: =COUNTIF($G$3:$G$19, L3) / COUNT($F$3:$G$19) -> 0.35294118
C5: Telephones and Communication | D5: 198764.49 | E5: 0.10328981 | F5: 0.40429849 | G5: =IF(F5 <= 80%, "A", IF(F5 <= 95%, "B", "C")) -> A | I5: процент выручки | J5: =SUMIF($G$3:$G$19, J3, $D$3:$D$19) / SUM($D$3:$D$19) -> 0.74982326 | K5: =SUMIF($G$3:$G$19, K3, $D$3:$D$19) / SUM($D$3:$D$19) -> 0.19518549 | L5: =SUMIF($G$3:$G$19, L3, $D$3:$D$19) / SUM($D$3:$D$19) -> 0.054991242
C6: Tables | D6: 193764.58 | E6: 0.10069156 | F6: 0.50499005 | G6: =IF(F6 <= 80%, "A", IF(F6 <= 95%, "B", "C")) -> A
C7: Binders and Binder Accessories | D7: 185928.14 | E7: 0.09661928 | F7: 0.60160933 | G7: =IF(F7 <= 80%, "A", IF(F7 <= 95%, "B", "C")) -> A
C8: Storage & Organization | D8: 177417.6 | E8: 0.092196699 | F8: 0.69380603 | G8: =IF(F8 <= 80%, "A", IF(F8 <= 95%, "B", "C")) -> A
C9: Bookcases | D9: 107796.09 | E9: 0.056017236 | F9: 0.74982326 | G9: =IF(F9 <= 80%, "A", IF(F9 <= 95%, "B", "C")) -> A
C10: Copiers and Fax | D10: 99069.48 | E10: 0.051482373 | F10: 0.80130564 | G10: =IF(F10 <= 80%, "A", IF(F10 <= 95%, "B", "C")) -> B
C11: Office Furnishings | D11: 98070.91 | E11: 0.050963457 | F11: 0.85226909 | G11: =IF(F11 <= 80%, "A", IF(F11 <= 95%, "B", "C")) -> B
C12: Computer Peripherals | D12: 96261.3 | E12: 0.050023076 | F12: 0.90229217 | G12: =IF(F12 <= 80%, "A", IF(F12 <= 95%, "B", "C")) -> B
C13: Appliances | D13: 82201.15 | E13: 0.042716589 | F13: 0.94500876 | G13: =IF(F13 <= 80%, "A", IF(F13 <= 95%, "B", "C")) -> B
C14: Paper | D14: 55813.92 | E14: 0.02900422 | F14: 0.97401298 | G14: =IF(F14 <= 80%, "A", IF(F14 <= 95%, "B", "C")) -> C
C15: Pens & Art Supplies | D15: 26071.61 | E15: 0.013548354 | F15: 0.98756133 | G15: =IF(F15 <= 80%, "A", IF(F15 <= 95%, "B", "C")) -> C
C16: Envelopes | D16: 10479.77 | E16: 0.0054459095 | F16: 0.99300724 | G16: =IF(F16 <= 80%, "A", IF(F16 <= 95%, "B", "C")) -> C
C17: Scissors, Rulers and Trimmers | D17: 6752.18 | E17: 0.0035088329 | F17: 0.99651607 | G17: =IF(F17 <= 80%, "A", IF(F17 <= 95%, "B", "C")) -> C
... C19: Rubber Bands | D19: 1789.43 | E19: 0.00092989387 | F19: 1 | G19: =IF(F19 <= 80%, "A", IF(F19 <= 95%, "B", "C")) -> C
C20: Общий итог | D20: 1924337.9 | E20: 1

Sheet products
A1: Product_id | B1: Product Category | C1: Product Sub-Category | D1: Product Name
A2: 15 | B2: Office Supplies | C2: Paper | D2: Xerox 194
A3: 27 | B3: Office Supplies | C3: Paper | D3: Xerox 1903
A4: 30 | B4: Office Supplies | C4: Paper | D4: Xerox 193
A5: 31 | B5: Office Supplies | C5: Paper | D5: Snap-A-Way® Black Print Carbonless Speed Message, No Reply Area, Duplicate
A6: 44 | B6: Office Supplies | C6: Paper | D6: Array® Memo Cubes
A7: 46 | B7: Office Supplies | C7: Paper | D7: REDIFORM Incoming/Outgoing Call Register, 11" X 8 1/2", 100 Messages
A8: 47 | B8: Office Supplies | C8: Paper | D8: Xerox 1897
A9: 56 | B9: Office Supplies | C9: Paper | D9: EcoTones® Memo Sheets
A10: 63 | B10: Office Supplies | C10: Paper | D10: Xerox 1939
A11: 65 | B11: Office Supplies | C11: Paper | D11: Xerox 1964
A12: 66 | B12: Office Supplies | C12: Paper | D12: Wirebound Message Books, 2 7/8" x 5", 3 Forms per Page
A13: 79 | B13: Office Supplies | C13: Paper | D13: Xerox 1952
... A914: 913 | B914: Furniture | C914: Office Furnishings | D914: Tenex 46" x 60" Computer Anti-Static Chairmat, Rectangular Shaped
